Workbook

Sheet Admin
A1: Company Categores | C1: Strat | E1: Priority | G1: Status | I1: Aviation Lookup
A2: Parts Supplier | C2: No Alignment | E2: Low | G2: Done | I2: Category | J2: Scope of Work
A3: AMO | C3: Approved Supplier | E3: Medium | G3: Contacted - Email | I3: A | J3: Line maintenance on aircraft airframes (release to service, minor assembly, certifying install and test/ferry flights)
A4: AMO - Heli | C4: Client | E4: High | G4: NTC | I4: B | J4: Component-level maintenance for airframes and accessories (rotorcraft excluded from engine)
A5: Charter | C5: Partnership | E5: Imminent | G5: Investigate | I5: C | J5: On‑wing maintenance for engines (non‑rotorcraft), including test flight release
A6: Charter - Heli | C6: Convert - Serial Number | G6: DNC | I6: D | J6: Rack-level engine work (overhaul, repair, modifications), plus manufacture of parts under CAR 21
A7: Insurance | G7: Closed | I7: E | J7: Rotorcraft and rotorcraft‑engine maintenance (airframe/engine installs, overhaul, rotors, test‑flight release)
A8: Underwriter | G8: Cape Town | I8: W | J8: Installation and maintenance of aircraft electrical, instrument, and radio systems across all aircraft classes
A9: Brokers | G9: Last Order | I9: X | J9: Overhaul, repair, testing, modification, and limited manufacture of equipment, instruments, components, accessories, auxiliaries, parts (e.g. propellers class X4, welding class X5)
A10: Flight School | G10: Edrich
A11: Commercial | G11: Likely Closed
A12: Motorsport

Sheet Company_Cat
A1: C_ID | B1: Company | C1: QuickNooks_Name | D1: Last_Order_Date | E1: Category | F1: Strat | G1: Priority | H1: Status | I1: LoadDate | J1: Checked | K1: Website
A2: 1 | B2: 208 Aviation CC | C2: 208 Aviation CC | D2: 45810 | E2: Unspecified | G2: Low | H2: Investigate | I2: 1970-01-01 | K2: https://www.santam.co.za/insurance/for-specialised-risks/aviation/
A3: 2 | B3: 360 Aviation | C3: 360 Aviation | E3: AMO - Heli | F3: Client | G3: Low | H3: Contacted | I3: 2025-07-01 | K3: https://itoo.co.za
A4: 3 | B4: 43 Air School | C4: 43 Air School | E4: Unspecified | G4: Low | H4: Investigate | I4: 1970-01-01
A5: 4 | B5: 4aviators | C5: 4aviators | E5: Flight School | G5: Low | H5: Unknown | I5: 1970-01-01 | K5: https://www.infinitiafrica.com
A6: 5 | B6: Absolute Service Centre (Pty) Ltd | C6: Absolute Service Centre | D6: 42247 | E6: Unspecified | G6: Low | H6: Investigate | I6: 1970-01-01
A7: 6 | B7: Academy Air | C7: Acadamy Air Charl Truter | D7: 41550 | E7: Unspecified | G7: Low | H7: Investigate | I7: 1970-01-01 | K7: https://www.aig.com/home/risk-solutions/business/specialty-risks/aerospace-and-aviation#accordion-df98a3f1db-item-e1731f5793
A8: 7 | B8: Acher Aviation | C8: Acher Aviation Helicopters | D8: 45859 | E8: Unspecified | G8: Low | H8: Investigate | I8: 1970-01-01
A9: 8 | B9: ADT Heliworx | C9: ADT Heliworx | E9: Unspecified | G9: Low | H9: Investigate | I9: 1970-01-01
A10: 9 | B10: Advanced Technologies & Engineering(PTY)Ltd t/a Paramount Aerospace Systemes | C10: Advanced Technologies & Engineering(PTY)Ltd t/a Paramount Aerospace Systemes | E10: Unspecified | G10: Low | H10: Investigate | I10: 1970-01-01
A11: 10 | B11: Adventure Air | C11: Adventure Air | D11: 44586 | E11: Unspecified | G11: Low | H11: Investigate | I11: 1970-01-01
A12: 11 | B12: Aero Electrical Solutions | C12: Aero Electrical Solutions | E12: Unspecified | G12: Low | H12: Investigate | I12: 1970-01-01
A13: 12 | B13: Aero Engineering and Powerplant | C13: Aero Engineering and Powerplant | E13: Unspecified | G13: Low | H13: Investigate | I13: 1970-01-01
A14: 13 | B14: Aero Maintenance Centre CC | C14: Aero Maintenance Centre CC | E14: Unspecified | G14: Low | H14: Investigate | I14: 1970-01-01
A15: 14 | B15: Aero Natal (Pty) Ltd | C15: Aero Natal (Pty) Ltd | E15: Unspecified | G15: Low | H15: Investigate | I15: 1970-01-01
A16: 15 | B16: Aero Services Pty Ltd | C16: Aero Services Pty Ltd | E16: Unspecified | G16: Low | H16: Investigate | I16: 1970-01-01
A17: 16 | B17: Aero Test NDT cc | C17: Aero Test NDT cc | E17: Unspecified | G17: Low | H17: Investigate | I17: 1970-01-01
A18: 17 | B18: AEROCORPORATION AVIATION SERVICES AMO (Pty) Ltd | C18: AEROCORPORATION AVIATION SERVICES AMO (Pty) Ltd | E18: Unspecified | G18: Low | H18: Investigate | I18: 1970-01-01 | K18: https://www.flightsure.co.za/
A19: 18 | B19: AEROMARITIME MEDITERRANEAN- MALTA | C19: AEROMARITIME MEDITERRANEAN- MALTA | E19: Unspecified | G19: Low | H19: Investigate | I19: 1970-01-01 | K19: https://www.arcaviation.co.za/
A20: 19 | B20: Aeronautic Solutions (Pty) Ltd | C20: Aeronautic Solutions (Pty) Ltd | E20: Unspecified | G20: Low | H20: Investigate | I20: 1970-01-01
A21: 20 | B21: Aeronautical Aviation | C21: Aeronautical Aviation | E21: Unspecified | G21: Low | H21: Investigate | I21: 1970-01-01
A22: 21 | B22: Aeronexus Corporate (PTY) LTD | C22: Aeronexus | D22: 38818 | E22: Unspecified | G22: Low | H22: Investigate | I22: 1970-01-01
A23: 22 | B23: Aerospace Electroplating CC | C23: Aerospace Electroplating CC | E23: Unspecified | G23: Low | H23: Investigate | I23: 1970-01-01 | K23: https://pilotinsure.co.za
A24: 23 | B24: Aerotec | C24: Aerotec | E24: Unspecified | G24: Low | H24: Investigate | I24: 1970-01-01
A25: 24 | B25: AEROTRIC (Pty)Ltd | C25: AEROTRIC (Pty)Ltd | E25: Unspecified | G25: Low | H25: Investigate | I25: 1970-01-01 | K25: https://4aviators.com/
A26: 25 | B26: Aeroweld & Supplies | C26: Aeroweld & Supplies | E26: Unspecified | G26: Low | H26: Investigate | I26: 1970-01-01 | K26: https://agmfsg.co.za/specialist-insurance-commercial/
A27: 26 | B27: Afritec Aviation Services | C27: Afritec Aviation Services | E27: Unspecified | G27: Low | H27: Investigate | I27: 1970-01-01
A28: 27 | B28: Against The Wind | C28: Against The Wind | E28: Unspecified | G28: Low | H28: Investigate | I28: 1970-01-01
A29: 28 | B29: AGM | C29: AGM | E29: Insurance | F29: Approved Supplier | G29: Low | H29: Unknown | I29: 1970-01-01
A30: 29 | B30: Aiforce Turbine Services Texas | C30: Aiforce Turbine Services Texas | E30: Unspecified | G30: Low | H30: Investigate | I30: 1970-01-01
A31: 30 | B31: AIG South Africa | C31: AIG South Africa | E31: Insurance | F31: Approved Supplier | G31: Low | H31: Done | I31: 2025-07-14 | J31: 1
A32: 31 | B32: AIR EXPRESS ALGERIA | C32: AIR EXPRESS ALGERIA | E32: Unspecified | G32: Low | H32: Investigate | I32: 1970-01-01
A33: 32 | B33: Air Hart Aircraft CC. | C33: Air Hart Aircraft | D33: 37512 | E33: Unspecified | G33: Low | H33: Investigate | I33: 1970-01-01
A34: 33 | B34: Air Mauritius Ltd | C34: Air Mauritius Ltd | E34: Unspecified | G34: Low | H34: Investigate | I34: 1970-01-01
A35: 34 | B35: Air Serve | C35: Air Serve | E35: Unspecified | G35: Low | H35: Investigate | I35: 1970-01-01
A36: 35 | B36: Airborne Insurance Consultants (PSG Insure) | C36: Airborne Insurance Consultants (PSG Insure) | E36: Brokers | F36: Approved Supplier | G36: Low | H36: Unknown | I36: 1970-01-01
A37: 36 | B37: Airbus Southern Africa (Pty) Ltd | C37: Airbus Southern Africa (Pty) Ltd | E37: Unspecified | G37: Low | H37: Investigate | I37: 1970-01-01
A38: 37 | B38: AIRCRAFT FUSELAGE REPAIRS | C38: AIRCRAFT FUSELAGE REPAIRS | E38: Unspecified | G38: Low | H38: Investigate | I38: 1970-01-01
A39: 38 | B39: Aircraft Instruments CC | C39: Aircraft Instruments CC | E39: Unspecified | G39: Low | H39: Investigate | I39: 1970-01-01
A40: 39 | B40: Aircraft Maintenance @ work | C40: Aircraft Maintenance @ work | E40: Unspecified | G40: Low | H40: Investigate | I40: 1970-01-01
A41: 40 | B41: Aircraft Maintenance Personnel (Pty) Ltd | C41: Aircraft Maintenance Personnel (Pty) Ltd | E41: Unspecified | G41: Low | H41: Investigate | I41: 1970-01-01
A42: 41 | B42: Aircraft Powerplant Company (Pty) Ltd | C42: Aircraft Powerplant Company (Pty) Ltd | E42: Unspecified | G42: Low | H42: Investigate | I42: 1970-01-01
A43: 42 | B43: AIRCRAFT UNLIMITED | C43: AIRCRAFT UNLIMITED | E43: Unspecified | G43: Low | H43: Investigate | I43: 1970-01-01
A44: 43 | B44: Air-Tec Aviation Maintenance (Pty) Ltd | C44: Air tech bethlehem | D44: 41171 | E44: Unspecified | G44: Low | H44: Investigate | I44: 1970-01-01
A45: 44 | B45: AIRVENTURES HOT AIR BALLOONING CC | C45: AIRVENTURES HOT AIR BALLOONING CC | E45: Unspecified | G45: Low | H45: Investigate | I45: 1970-01-01 | K45: https://www.lowveldaircraft.co.za/contact_us.htm
A46: 45 | B46: AIRWORK AFRICA | C46: AIRWORK AFRICA | E46: Unspecified | G46: Low | H46: Investigate | I46: 1970-01-01
A47: 46 | B47: Airwork Aviation Maintenance Division (Pty) Ltd | C47: Airwork Aviation Maintenance Division (Pty) Ltd | E47: Unspecified | G47: Low | H47: Investigate | I47: 1970-01-01
A48: 47 | B48: AIRWORK NEW ZEALAND/CONAKRY | C48: AIRWORK NEW ZEALAND/CONAKRY | E48: Unspecified | G48: Low | H48: Investigate | I48: 1970-01-01
A49: 48 | B49: Allianz Commercial | C49: Allianz Commercial | E49: Insurance | F49: Approved Supplier | G49: Low | H49: Unknown | I49: 1970-01-01
A50: 49 | B50: ALR Flight Investments PTY (LTD) | C50: ALR FLIGHT INVESTMENT | D50: 45728 | E50: Unspecified | G50: Low | H50: Investigate | I50: 1970-01-01
A51: 50 | B51: Alton Aero Engineering (Pty) Ltd | C51: Alton Aero Eng | D51: 45840 | E51: Unspecified | G51: Low | H51: Investigate | I51: 1970-01-01
A52: 51 | B52: ALTON GROUP OF COMPANIES (VASLOSCENE) | C52: ALTON GROUP OF COMPANIES (VASLOSCENE) | E52: Unspecified | G52: Low | H52: Investigate | I52: 1970-01-01
A53: 52 | B53: AME Aviation | C53: AME Aviation | E53: Unspecified | G53: Low | H53: Investigate | I53: 1970-01-01
A54: 53 | B54: AMKA Aviation (PTY) Ltd | C54: AMKA Aviation (PTY) Ltd | E54: Unspecified | G54: Low | H54: Investigate | I54: 1970-01-01
A55: 54 | B55: Aon South Africa (Aviation Division) | C55: Aon South Africa (Aviation Division) | E55: Brokers | F55: Approved Supplier | G55: Low | H55: Unknown | I55: 1970-01-01
A56: 55 | B56: Aquila Air Services | C56: Aquila Air Services | E56: Unspecified | G56: Low | H56: Investigate | I56: 1970-01-01
A57: 56 | B57: Arc Aviation (Aircraft Risk Company) | C57: Arc Aviation (Aircraft Risk Company) | E57: Brokers | F57: Approved Supplier | G57: Medium | H57: Contacted - Email | I57: 2025-07-15 | J57: 1
A58: 57 | B58: AREF Avionics | C58: AREF Avionics | E58: Unspecified | G58: Low | H58: Investigate | I58: 1970-01-01
A59: 58 | B59: Aspire Aviation (Former name Lanseria Jet Centre) | C59: Aspire Aviation (Former name Lanseria Jet Centre) | E59: Unspecified | G59: Low | H59: Investigate | I59: 1970-01-01
A60: 59 | B60: Astwood Aircraft Electrical CC | C60: Astwood Aircraft Electrical CC | E60: Unspecified | G60: Low | H60: Investigate | I60: 1970-01-01
A61: 60 | B61: Aves Technics | C61: Aves Technics | E61: Unspecified | G61: Low | H61: Investigate | I61: 1970-01-01
A62: 61 | B62: Avex Air Technical | C62: Avex Air Technical | E62: Unspecified | G62: Low | H62: Investigate | I62: 1970-01-01
A63: 62 | B63: Avia Instruments | C63: Avia Instruments | E63: Unspecified | G63: Low | H63: Investigate | I63: 1970-01-01
A64: 63 | B64: Aviation Dynamix | C64: Aviation Dynamix | E64: Unspecified | G64: Low | H64: Investigate | I64: 1970-01-01 | K64: https://ferreiraaviation.co.za/contact/
A65: 64 | B65: Aviation Rebuilders CC | C65: Aviation Rebuilders CC | E65: Unspecified | G65: Low | H65: Investigate | I65: 1970-01-01
A66: 65 | B66: Avisys Aviation System | C66: Avisys Aviation System | E66: Unspecified | G66: Low | H66: Investigate | I66: 1970-01-01
A67: 66 | B67: Avtech Aircraft Services CC | C67: Avtech Aircraft Services CC | E67: Unspecified | G67: Low | H67: Investigate | I67: 1970-01-01
A68: 67 | B68: Axella Aeronautical Engineering | C68: Axella Aeronautical Engineering | E68: Unspecified | G68: Low | H68: Investigate | I68: 1970-01-01
A69: 68 | B69: Azriel Aero | C69: Azriel Aero | E69: Brokers | F69: Approved Supplier | G69: Low | H69: Unknown | I69: 1970-01-01
A70: 69 | B70: Azriel Aviation | C70: Azriel Aviation | E70: Insurance | F70: Approved Supplier | G70: Low | H70: Unknown | I70: 1970-01-01
A71: 70 | B71: Aztec Electronics (Pty) Ltd | C71: Aztec Electronics (Pty) Ltd | E71: Unspecified | G71: Low | H71: Investigate | I71: 1970-01-01
A72: 71 | B72: BAC Aviation (Pty) Ltd | C72: BAC Aviation (Pty) Ltd | E72: Unspecified | G72: Low | H72: Investigate | I72: 1970-01-01
A73: 72 | B73: Balloon Workshop | C73: Balloon Workshop | E73: Unspecified | G73: Low | H73: Investigate | I73: 1970-01-01
A74: 73 | B74: Bay Aircraft Services | C74: Bay Aircraft Services | E74: Unspecified | G74: Low | H74: Investigate | I74: 1970-01-01
A75: 74 | B75: Bedek Aviation Group | C75: Bedek Aviation Group | E75: Unspecified | G75: Low | H75: Investigate | I75: 1970-01-01
A76: 75 | B76: Bedshemesh | C76: Bedshemesh | E76: Unspecified | G76: Low | H76: Investigate | I76: 1970-01-01
A77: 76 | B77: BHAKARI AVIATION SERVICES | C77: BHAKARI AVIATION SERVICES | E77: Unspecified | G77: Low | H77: Investigate | I77: 1970-01-01
A78: 77 | B78: Blue Bird Aviation | C78: Blue Bird Aviation | E78: Unspecified | G78: Low | H78: Investigate | I78: 1970-01-01
A79: 78 | B79: BNT International (Pty) LTD | C79: BNT International (Pty) LTD | E79: Unspecified | G79: Low | H79: Investigate | I79: 1970-01-01
A80: 79 | B80: Bombardier Services (UK) Ltd | C80: Bombardier Services (UK) Ltd | E80: Unspecified | G80: Low | H80: Investigate | I80: 1970-01-01
A81: 80 | B81: Breytech Aviation cc | C81: Breytech Aviation cc | E81: Unspecified | G81: Low | H81: Investigate | I81: 1970-01-01
A82: 81 | B82: British Airways Engineering | C82: British Airways Engineering | E82: Unspecified | G82: Low | H82: Investigate | I82: 1970-01-01
A83: 82 | B83: Bryte Insurance (Zurich SA) | C83: Bryte Insurance (Zurich SA) | E83: Insurance | F83: Approved Supplier | G83: Low | H83: Unknown | I83: 1970-01-01
A84: 83 | B84: Buck Rogers Aviation | C84: Buck Rogers Aviation | E84: Unspecified | G84: Low | H84: Investigate | I84: 1970-01-01
A85: 84 | B85: Cape Aircraft Interiors | C85: Cape Aircraft Interiors | E85: Unspecified | G85: Low | H85: Investigate | I85: 1970-01-01
A86: 85 | B86: Capital Air (Pty) Ltd | C86: capital air | D86: 45853 | E86: Unspecified | G86: Low | H86: Last Order | I86: 2025-07-15
A87: 86 | B87: Cathay Pacific | C87: Cathay Pacific | E87: Unspecified | G87: Low | H87: Investigate | I87: 1970-01-01
A88: 87 | B88: CEMAIR (PTY) LTD | C88: CEMAIR (PTY) LTD | E88: Unspecified | G88: Low | H88: Investigate | I88: 1970-01-01
A89: 88 | B89: Cemys Aircraft Structures Repairs | C89: Cemys Aircraft Structures Repairs | E89: Unspecified | G89: Low | H89: Investigate | I89: 1970-01-01
A90: 89 | B90: Century Avionics CC | C90: Century Avionics CC | E90: Unspecified | G90: Low | H90: Investigate | I90: 1970-01-01
A91: 90 | B91: CIRRUS Africa | C91: CIRRUS Africa | E91: Unspecified | G91: Low | H91: Investigate | I91: 1970-01-01
A92: 91 | B92: Clack Air CC | C92: Clack Air CC | E92: Unspecified | G92: Low | H92: Investigate | I92: 1970-01-01
A93: 92 | B93: Clifton Electronics CC | C93: Clifton Electronics CC | E93: Unspecified | G93: Low | H93: Investigate | I93: 1970-01-01
A94: 93 | B94: COMAIR LIMITED | C94: COMAIR LIMITED | E94: Unspecified | G94: Low | H94: Investigate | I94: 1970-01-01
A95: 94 | B95: Constantia Insurance | C95: Constantia Insurance | E95: Underwriter | F95: Approved Supplier | G95: Low | H95: Unknown | I95: 1970-01-01
A96: 95 | B96: Covington Aircraft Services | C96: Covington Aircraft Services | E96: Unspecified | G96: Low | H96: Investigate | I96: 1970-01-01
A97: 96 | B97: Cronos Airlines International (Pty) LTD | C97: Cronos Airlines International (Pty) LTD | E97: Unspecified | G97: Low | H97: Investigate | I97: 1970-01-01
A98: 97 | B98: Dart Aeronautical (Pty) Ltd | C98: Dart Aeronautical (Pty) Ltd | E98: Unspecified | G98: Low | H98: Investigate | I98: 1970-01-01
A99: 98 | B99: Dart Aircraft Electrical | C99: Dart Aircraft Electrical | E99: Unspecified | G99: Low | H99: Investigate | I99: 1970-01-01
A100: 99 | B100: Dassault Falcon Service | C100: Dassault Falcon Service | E100: Unspecified | G100: Low | H100: Investigate | I100: 1970-01-01
...

Sheet Order Dates
A1: Company_QuickBooks+ | B1: Order_Dates | C1: Once-Off | D1: Captured
A2: Acher Aviation Helicopters | B2: 45859 | D2: =IFERROR(VLOOKUP($A2,Company_Cat!$C$2:$C$623,1,FALSE),"")
A3: ms FAST DEVELOPMENT CC | B3: 45855 | D3: =IFERROR(VLOOKUP($A3,Company_Cat!$C$2:$C$623,1,FALSE),"")
A4: ms Pablo Clark | B4: 45855 | D4: =IFERROR(VLOOKUP($A4,Company_Cat!$C$2:$C$623,1,FALSE),"")
A5: ms Stradale Motorsport | B5: 45855 | D5: =IFERROR(VLOOKUP($A5,Company_Cat!$C$2:$C$623,1,FALSE),"")
A6: Skytrim rico | B6: 45855 | D6: =IFERROR(VLOOKUP($A6,Company_Cat!$C$2:$C$623,1,FALSE),"")
A7: capital air | B7: 45853 | D7: =IFERROR(VLOOKUP($A7,Company_Cat!$C$2:$C$623,1,FALSE),"")
A8: Sky Hunter South Africa | B8: 45848 | D8: =IFERROR(VLOOKUP($A8,Company_Cat!$C$2:$C$623,1,FALSE),"")
A9: Alton Aero Eng | B9: 45840 | D9: =IFERROR(VLOOKUP($A9,Company_Cat!$C$2:$C$623,1,FALSE),"")
A10: TAM | B10: 45838 | D10: =IFERROR(VLOOKUP($A10,Company_Cat!$C$2:$C$623,1,FALSE),"")
A11: Aviation Rebuilders | B11: 45827 | D11: =IFERROR(VLOOKUP($A11,Company_Cat!$C$2:$C$623,1,FALSE),"")
A12: Heli-Fix cc | B12: 45826 | D12: =IFERROR(VLOOKUP($A12,Company_Cat!$C$2:$C$623,1,FALSE),"")
A13: ms Nishal Autonische | B13: 45819 | D13: =IFERROR(VLOOKUP($A13,Company_Cat!$C$2:$C$623,1,FALSE),"")
... A320: Acryl Form | B320: 40221 | D320: =IFERROR(VLOOKUP($A320,Company_Cat!$C$2:$C$623,1,FALSE),"")
A321: A R Cook | B321: 40219 | C321: 1 | D321: =IFERROR(VLOOKUP($A321,Company_Cat!$C$2:$C$623,1,FALSE),"")
A322: Harry Leach Trust | B322: 40219 | D322: =IFERROR(VLOOKUP($A322,Company_Cat!$C$2:$C$623,1,FALSE),"")
A323: ms Misubishi Raptor Engineering | B323: 40200 | D323: =IFERROR(VLOOKUP($A323,Company_Cat!$C$2:$C$623,1,FALSE),"")
A324: KAE | B324: 40196 | D324: =IFERROR(VLOOKUP($A324,Company_Cat!$C$2:$C$623,1,FALSE),"")
A325: Vernon Smith | B325: 40161 | D325: =IFERROR(VLOOKUP($A325,Company_Cat!$C$2:$C$623,1,FALSE),"")
A326: ms RG Motorsport | B326: 40135 | D326: =IFERROR(VLOOKUP($A326,Company_Cat!$C$2:$C$623,1,FALSE),"")
A327: Diesel Aviation | B327: 40092 | D327: =IFERROR(VLOOKUP($A327,Company_Cat!$C$2:$C$623,1,FALSE),"")
A328: Spingbok Aviation | B328: 40084 | D328: =IFERROR(VLOOKUP($A328,Company_Cat!$C$2:$C$623,1,FALSE),"")
A329: Omni | B329: 40052 | D329: =IFERROR(VLOOKUP($A329,Company_Cat!$C$2:$C$623,1,FALSE),"")
A330: DENEL SAAB AEROSTRUCTURES (PTY) LTD | B330: 40040 | D330: =IFERROR(VLOOKUP($A330,Company_Cat!$C$2:$C$623,1,FALSE),"")
A331: Duraset Visagie | B331: 40022 | D331: =IFERROR(VLOOKUP($A331,Company_Cat!$C$2:$C$623,1,FALSE),"")
A332: ms Porche Dave Fourie | B332: 39994 | D332: =IFERROR(VLOOKUP($A332,Company_Cat!$C$2:$C$623,1,FALSE),"")
A333: ms Village Auto | B333: 39975 | D333: =IFERROR(VLOOKUP($A333,Company_Cat!$C$2:$C$623,1,FALSE),"")
... A554: Hunting Aviation | B554: 35326 | D554: =IFERROR(VLOOKUP($A554,Company_Cat!$C$2:$C$623,1,FALSE),"")

Sheet Sheet1
A1: Abbot Cars | B1: ms Abbot Cars | C1: 41568
A2: Spannerworx | B2: ms Alpha Romeo Trevor Tuck | C2: 42032
A3: Allwagen | B3: ms Allwagen | C3: 44376
A4: Exclusive Conversions | B4: ms Anton Decker
A5: Auby Boys Racing | B5: ms Auby Boys Racing | C5: 41002
A6: Auto Associates | B6: ms Auto Associates | C6: 41724
A7: AutoCom | B7: ms AutoCom | C7: 41574
A8: Autohaus Angel | B8: ms Autohaus Angel | C8: 43735
A9: Azoic Panelbeaters | B9: ms Azoic | C9: 42563
A10: Seven mile trading 424 cc T/A B Speed | B10: ms B Speed | C10: 44440
A11: Randfontein Paneelkloppers | B11: ms Ben Morgenrood | C11: 40751
A12: Wayne Niz | B12: ms BMW Wayne Niz | C12: 41225
A13: Evolution 2 Motorsport | B13: ms BMW Kaye Eddie | C13: 38182
A14: BMW Montana | B14: ms BMW Montana | C14: 44235
A15: BMW South Africa (SA) (Pty) Ltd | B15: ms BMW Motorsport | C15: 39447
A16: Riaan | B16: ms BMW Riaan | C16: 39447
... A47: JSR | B47: ms Honda JSR | C47: 40581

Sheet Company_Contacts
A1: C_ID | B1: Company | C1: Status | D1: FirstName | E1: Surname | F1: Position | G1: Cellnumber | H1: Email | I1: Landline
A2: =IFERROR(VLOOKUP($B2,Company_Cat!$B$2:$E$623,2,FALSE),"") | B2: Flightsure | C2: =IFERROR(VLOOKUP($B2,Company_Cat!$B$2:$H$623,6,FALSE),"") | D2: Dorrien Andrews | F2: Director | G2: 27832269672 | H2: dorrien@flightsure.co.za
A3: =IFERROR(VLOOKUP($B3,Company_Cat!$B$2:$E$623,2,FALSE),"") | B3: Flightsure | C3: =IFERROR(VLOOKUP($B3,Company_Cat!$B$2:$H$623,6,FALSE),"") | D3: Mandy Coetzer | F3: Director | G3: 27824483643 | H3: mandy@flightsure.co.za
A4: =IFERROR(VLOOKUP($B4,Company_Cat!$B$2:$E$623,2,FALSE),"") | B4: Flightsure | C4: =IFERROR(VLOOKUP($B4,Company_Cat!$B$2:$H$623,6,FALSE),"") | D4: Gaile Mendes | F4: Director | G4: 27828501857 | H4: gaile@flightsure.co.za
A5: =IFERROR(VLOOKUP($B5,Company_Cat!$B$2:$E$623,2,FALSE),"") | B5: Flightsure | C5: =IFERROR(VLOOKUP($B5,Company_Cat!$B$2:$H$623,6,FALSE),"") | D5: Glenn Andrews | F5: Director | G5: 27832597581
A6: =IFERROR(VLOOKUP($B6,Company_Cat!$B$2:$E$623,2,FALSE),"") | B6: Arc Aviation (Aircraft Risk Company) | C6: =IFERROR(VLOOKUP($B6,Company_Cat!$B$2:$H$623,6,FALSE),"") | D6: Stuart Farquhar | F6: MD | G6: 27824432633 | H6: stuart@arcaviation.co.za
A7: =IFERROR(VLOOKUP($B7,Company_Cat!$B$2:$E$623,2,FALSE),"") | B7: Arc Aviation (Aircraft Risk Company) | C7: =IFERROR(VLOOKUP($B7,Company_Cat!$B$2:$H$623,6,FALSE),"") | D7: Darren Gallias | F7: Director - Claims Manager | G7: 27833777190 | H7: darren@arcaviation.co.za
A8: =IFERROR(VLOOKUP($B8,Company_Cat!$B$2:$E$623,2,FALSE),"") | B8: Arc Aviation (Aircraft Risk Company) | C8: =IFERROR(VLOOKUP($B8,Company_Cat!$B$2:$H$623,6,FALSE),"") | D8: Dylan Knight | F8: New Business Broker | G8: 27725290273 | H8: dylan@arcaviation.co.za
A9: =IFERROR(VLOOKUP($B9,Company_Cat!$B$2:$E$623,2,FALSE),"") | B9: Arc Aviation (Aircraft Risk Company) | C9: =IFERROR(VLOOKUP($B9,Company_Cat!$B$2:$H$623,6,FALSE),"") | D9: Tshidi Ntsoseng | F9: Accounts | G9: 27734323112 | H9: tshidi@arcaviation.co.za
A10: =IFERROR(VLOOKUP($B10,Company_Cat!$B$2:$E$623,2,FALSE),"") | B10: Arc Aviation (Aircraft Risk Company) | C10: =IFERROR(VLOOKUP($B10,Company_Cat!$B$2:$H$623,6,FALSE),"") | D10: Clement Sibiya | F10: Accounts Executive | G10: 27713391251 | H10: clement@arcaviation.co.za
A11: =IFERROR(VLOOKUP($B11,Company_Cat!$B$2:$E$623,2,FALSE),"") | B11: Arc Aviation (Aircraft Risk Company) | C11: =IFERROR(VLOOKUP($B11,Company_Cat!$B$2:$H$623,6,FALSE),"") | D11: Janice Ray | F11: Senior Accounts Exec | G11: 27832926917 | H11: janice@arcaviation.co.za
A12: =IFERROR(VLOOKUP($B12,Company_Cat!$B$2:$E$623,2,FALSE),"") | B12: Arc Aviation (Aircraft Risk Company) | C12: =IFERROR(VLOOKUP($B12,Company_Cat!$B$2:$H$623,6,FALSE),"") | D12: Janette Harris | F12: Senior Accounts & Compliance Manager | G12: 27761580797 | H12: janette@arcaviation.co.za
A13: =IFERROR(VLOOKUP($B13,Company_Cat!$B$2:$E$623,2,FALSE),"") | B13: iTOO Special Risks (Hollard) | C13: =IFERROR(VLOOKUP($B13,Company_Cat!$B$2:$H$623,6,FALSE),"") | D13: Lorenzio Bettini | F13: Senior Underwriter | H13: LorenzioB@itoo.co.za
A14: =IFERROR(VLOOKUP($B14,Company_Cat!$B$2:$E$623,2,FALSE),"") | B14: Infiniti Insurance | C14: =IFERROR(VLOOKUP($B14,Company_Cat!$B$2:$H$623,6,FALSE),"") | D14: Carly Ranger | F14: Aviation Broker | G14: 27828570291 | H14: carlyr@infinitiaviation.co.za
A15: =IFERROR(VLOOKUP($B15,Company_Cat!$B$2:$E$623,2,FALSE),"") | B15: Infiniti Insurance | C15: =IFERROR(VLOOKUP($B15,Company_Cat!$B$2:$H$623,6,FALSE),"") | D15: Belinda Hawkins | F15: General Manager - Divisonal Head | H15: belindah@infinitiafrica.com | I15: 27117181200
A16: =IFERROR(VLOOKUP($B16,Company_Cat!$B$2:$E$623,2,FALSE),"") | B16: Infiniti Insurance | C16: =IFERROR(VLOOKUP($B16,Company_Cat!$B$2:$H$623,6,FALSE),"") | D16: Sharon Paterson | F16: CEO
A17: =IFERROR(VLOOKUP($B17,Company_Cat!$B$2:$E$623,2,FALSE),"") | B17: AIG South Africa | C17: =IFERROR(VLOOKUP($B17,Company_Cat!$B$2:$H$623,6,FALSE),"") | D17: Johannseburg Office | F17: Admin | G17: 27861488864
A18: =IFERROR(VLOOKUP($B18,Company_Cat!$B$2:$E$623,2,FALSE),"") | B18: iTOO Special Risks (Hollard) | C18: =IFERROR(VLOOKUP($B18,Company_Cat!$B$2:$H$623,6,FALSE),"") | D18: Willie | E18: Jansen van Rensburg | F18: Business Head - Claims | H18: WillieJ@itoo.co.za
A19: =IFERROR(VLOOKUP($B19,Company_Cat!$B$2:$E$623,2,FALSE),"") | B19: iTOO Special Risks (Hollard) | C19: =IFERROR(VLOOKUP($B19,Company_Cat!$B$2:$H$623,6,FALSE),"") | D19: Warwick | E19: Goldie | F19: Chief Underwriting Officer | H19: WarwickG@itoo.co.za
A20: =IFERROR(VLOOKUP($B20,Company_Cat!$B$2:$E$623,2,FALSE),"") | B20: iTOO Special Risks (Hollard) | C20: =IFERROR(VLOOKUP($B20,Company_Cat!$B$2:$H$623,6,FALSE),"") | D20: Jonathan | E20: Healy | F20: Managing Executive | H20: JonathanH@Itoo.co.za
A21: =IFERROR(VLOOKUP($B21,Company_Cat!$B$2:$E$623,2,FALSE),"") | B21: Orsmond Aviation | C21: =IFERROR(VLOOKUP($B21,Company_Cat!$B$2:$H$623,6,FALSE),"") | D21: Admin | G21: 27583035261 | H21: info@orsmondaviation.co.za
A22: =IFERROR(VLOOKUP($B22,Company_Cat!$B$2:$E$623,2,FALSE),"") | B22: MCC Aviation(PTY) Ltd | C22: =IFERROR(VLOOKUP($B22,Company_Cat!$B$2:$H$623,6,FALSE),"") | D22: Admin | H22: info@flymcc.co.za
A23: =IFERROR(VLOOKUP($B23,Company_Cat!$B$2:$E$623,2,FALSE),"") | B23: MCC Aviation(PTY) Ltd | C23: =IFERROR(VLOOKUP($B23,Company_Cat!$B$2:$H$623,6,FALSE),"") | D23: Micheal | E23: Goodwin | F23: General Manager | H23: mike.goodwin@flymcc.co.za
A24: =IFERROR(VLOOKUP($B24,Company_Cat!$B$2:$E$623,2,FALSE),"") | B24: Capital Air (Pty) Ltd | C24: =IFERROR(VLOOKUP($B24,Company_Cat!$B$2:$H$623,6,FALSE),"") | D24: Admin | H24: info@capitalairsa.com | I24: 27118270335
A25: =IFERROR(VLOOKUP($B25,Company_Cat!$B$2:$E$623,2,FALSE),"") | B25: MCC Aviation(PTY) Ltd | C25: =IFERROR(VLOOKUP($B25,Company_Cat!$B$2:$H$623,6,FALSE),"") | D25: Sean | E25: Murphy | F25: Helicopter AMO Manager | H25: sean.murphy@flymcc.co.za
A26: =IFERROR(VLOOKUP($B26,Company_Cat!$B$2:$E$623,2,FALSE),"") | B26: NAC Helicopter Division | C26: =IFERROR(VLOOKUP($B26,Company_Cat!$B$2:$H$623,6,FALSE),"") | D26: Ashley | E26: Spolander | F26: Helicopter Maintenance & Engine Shop Manager | H26: ashley.spolander@nac.co.za | I26: 27113452500
A27: =IFERROR(VLOOKUP($B27,Company_Cat!$B$2:$E$623,2,FALSE),"") | B27: SANPARKS | C27: =IFERROR(VLOOKUP($B27,Company_Cat!$B$2:$H$623,6,FALSE),"") | D27: Charles | E27: Phahlane | F27: Senior Communications Manager | G27: 27828568188 | H27: charles.phahlane@sanparks.org | I27: 27124265000
A28: =IFERROR(VLOOKUP($B28,Company_Cat!$B$2:$E$623,2,FALSE),"") | B28: Transvaal Aircraft Maintenance (Pty) Ltd | C28: =IFERROR(VLOOKUP($B28,Company_Cat!$B$2:$H$623,6,FALSE),"") | D28: Chris | E28: Korrf | I28: 27125671191
A29: =IFERROR(VLOOKUP($B29,Company_Cat!$B$2:$E$623,2,FALSE),"") | B29: Emperor Aviation Pty(Ltd) | C29: =IFERROR(VLOOKUP($B29,Company_Cat!$B$2:$H$623,6,FALSE),"") | D29: Paul | E29: Sankey | F29: CEO/Accountable Manager | G29: 27824971701 | H29: paul@emperoraviation.co.za
A30: =IFERROR(VLOOKUP($B30,Company_Cat!$B$2:$E$623,2,FALSE),"") | B30: PRECISION AVIATION SERVICES (PTY) Ltd | C30: =IFERROR(VLOOKUP($B30,Company_Cat!$B$2:$H$623,6,FALSE),"") | D30: Rikus | E30: Botha | H30: riks@pasaviation.co.za | I30: 27125430371
A31: =IFERROR(VLOOKUP($B31,Company_Cat!$B$2:$E$623,2,FALSE),"") | B31: BAC Aviation (Pty) Ltd | C31: =IFERROR(VLOOKUP($B31,Company_Cat!$B$2:$H$623,6,FALSE),"") | D31: Tremayne | E31: Thompson | F31: CEO/Accountable Manager | G31: 27837782635 | H31: tthompson@bacheli.com
A32: =IFERROR(VLOOKUP($B32,Company_Cat!$B$2:$E$623,2,FALSE),"") | B32: Lady Lori Kenya Limited | C32: =IFERROR(VLOOKUP($B32,Company_Cat!$B$2:$H$623,6,FALSE),"") | D32: Admin | G32: 27729850600 | H32: operations@flyladylori.com
A33: =IFERROR(VLOOKUP($B33,Company_Cat!$B$2:$E$623,2,FALSE),"") | B33: Ferreira Aviation CC | C33: =IFERROR(VLOOKUP($B33,Company_Cat!$B$2:$H$623,6,FALSE),"") | D33: Stanley | E33: Schimper | F33: Bloemfontein | G33: 27835576120 | H33: stanley@ferreiraaviation.co.za
A34: =IFERROR(VLOOKUP($B34,Company_Cat!$B$2:$E$623,2,FALSE),"") | B34: Ferreira Aviation CC | C34: =IFERROR(VLOOKUP($B34,Company_Cat!$B$2:$H$623,6,FALSE),"") | D34: Wyndham | E34: Ferreira | F34: Bloemfontein | G34: 27832620313 | H34: wyndham@ferreiraaviation.co.za
A35: =IFERROR(VLOOKUP($B35,Company_Cat!$B$2:$E$623,2,FALSE),"") | B35: Ferreira Aviation CC | C35: =IFERROR(VLOOKUP($B35,Company_Cat!$B$2:$H$623,6,FALSE),"") | D35: JP | F35: George | G35: 27843313964 | H35: jp@ferreiraaviation.co.za
A36: =IFERROR(VLOOKUP($B36,Company_Cat!$B$2:$E$623,2,FALSE),"") | B36: Lowveld Aircraft Services CC | C36: =IFERROR(VLOOKUP($B36,Company_Cat!$B$2:$H$623,6,FALSE),"") | D36: THOMAS | E36: WILLOWS | G36: 27823367262 | H36: twillows@mweb.co.za
A37: =IFERROR(VLOOKUP($B37,Company_Cat!$B$2:$E$623,2,FALSE),"") | B37: Lowveld Aircraft Services CC | C37: =IFERROR(VLOOKUP($B37,Company_Cat!$B$2:$H$623,6,FALSE),"") | D37: GARY | E37: VINCENT | G37: 27832940739 | H37: jvincent@vodamail.co.za
A38: =IFERROR(VLOOKUP($B38,Company_Cat!$B$2:$E$623,2,FALSE),"") | B38: PWR Aircraft Maintenance International | C38: =IFERROR(VLOOKUP($B38,Company_Cat!$B$2:$H$623,6,FALSE),"") | D38: Willie | E38: Pienaar | F38: Fixed Wing and Rotorcraft Maintainance Nelspruit | G38: 27827870415 | H38: ns@aminternational.co.za
A39: =IFERROR(VLOOKUP($B39,Company_Cat!$B$2:$E$623,2,FALSE),"") | B39: PWR Aircraft Maintenance International | C39: =IFERROR(VLOOKUP($B39,Company_Cat!$B$2:$H$623,6,FALSE),"") | D39: Willie | E39: Snyman | F39: Fixed Wing and Rotorcraft Maintainance Wonderboom | G39: 27824974687 | H39: wb@aminternational.co.za
A40: =IFERROR(VLOOKUP($B40,Company_Cat!$B$2:$E$623,2,FALSE),"") | B40: PWR Aircraft Maintenance International | C40: =IFERROR(VLOOKUP($B40,Company_Cat!$B$2:$H$623,6,FALSE),"") | D40: Pine | E40: Pienaar | F40: Aircraft Maintainance and Sales | G40: 27833050605 | H40: gm@aminternational.co.za
A41: =IFERROR(VLOOKUP($B41,Company_Cat!$B$2:$E$623,2,FALSE),"") | B41: Santam Aviation | C41: =IFERROR(VLOOKUP($B41,Company_Cat!$B$2:$H$623,6,FALSE),"") | D41: James | E41: Godden | F41: General | G41: 27828952765 | H41: james.godden@santam.co.za
A42: =IFERROR(VLOOKUP($B42,Company_Cat!$B$2:$E$623,2,FALSE),"") | B42: Santam Aviation | C42: =IFERROR(VLOOKUP($B42,Company_Cat!$B$2:$H$623,6,FALSE),"") | D42: Shirlene | E42: Frylinck | F42: Claims | G42: 27619443894 | H42: shirlene.frylinck@santam.co.za
A43: =IFERROR(VLOOKUP($B43,Company_Cat!$B$2:$E$623,2,FALSE),"") | B43: Santam Aviation | C43: =IFERROR(VLOOKUP($B43,Company_Cat!$B$2:$H$623,6,FALSE),"") | D43: Cleme | E43: Brown | F43: Underwriting | G43: 27833997802 | H43: cleme.brown@santam.co.za
A44: =IFERROR(VLOOKUP($B44,Company_Cat!$B$2:$E$623,2,FALSE),"") | B44: Vektor Aviation | C44: =IFERROR(VLOOKUP($B44,Company_Cat!$B$2:$H$623,6,FALSE),"") | D44: Reon | E44: Wiese | F44: CEO | G44: 27827861925 | H44: reon@vektoraviation.co.za
A45: =IFERROR(VLOOKUP($B45,Company_Cat!$B$2:$E$623,2,FALSE),"") | B45: Vektor Aviation | C45: =IFERROR(VLOOKUP($B45,Company_Cat!$B$2:$H$623,6,FALSE),"") | D45: Kim | E45: Van Der Walt | F45: Head of Aviation: Corporate & General Aviation | H45: kim@vektoraviation.co.za
A46: =IFERROR(VLOOKUP($B46,Company_Cat!$B$2:$E$623,2,FALSE),"") | B46: Vektor Aviation | C46: =IFERROR(VLOOKUP($B46,Company_Cat!$B$2:$H$623,6,FALSE),"") | D46: Leandra | E46: Rossel | F46: Aviation Operations Manager | H46: leandra@vektoraviation.co.za
A47: =IFERROR(VLOOKUP($B47,Company_Cat!$B$2:$E$623,2,FALSE),"") | B47: Greystones Aviaton Components (Pty) Ltd | C47: =IFERROR(VLOOKUP($B47,Company_Cat!$B$2:$H$623,6,FALSE),"") | H47: info@greystones.co.za | I47: 27310200901
A48: =IFERROR(VLOOKUP($B48,Company_Cat!$B$2:$E$623,2,FALSE),"") | B48: Airbus Southern Africa (Pty) Ltd | C48: =IFERROR(VLOOKUP($B48,Company_Cat!$B$2:$H$623,6,FALSE),"") | D48: Nam-Binh | E48: Hoang | F48: Service Manager | H48: nam-binh.hoang@airbus.com | I48: 27112662600
A49: =IFERROR(VLOOKUP($B49,Company_Cat!$B$2:$E$623,2,FALSE),"") | B49: Hover Dynamics Maintenance CC | C49: =IFERROR(VLOOKUP($B49,Company_Cat!$B$2:$H$623,6,FALSE),"") | D49: Willie | E49: Breitenbach | F49: Emergency Maintenance Manager | H49: hdm@hoverdynamics.co.za | I49: 27113157210
A50: =IFERROR(VLOOKUP($B50,Company_Cat!$B$2:$E$623,2,FALSE),"") | B50: Heli-Fix cc | C50: =IFERROR(VLOOKUP($B50,Company_Cat!$B$2:$H$623,6,FALSE),"") | H50: accounts@helifix.co.za
A51: =IFERROR(VLOOKUP($B51,Company_Cat!$B$2:$E$623,2,FALSE),"") | B51: Leading Edge Aviation cc | C51: =IFERROR(VLOOKUP($B51,Company_Cat!$B$2:$H$623,6,FALSE),"") | H51: office@leaviation.co.za | I51: 27125674905
A52: =IFERROR(VLOOKUP($B52,Company_Cat!$B$2:$E$623,2,FALSE),"") | B52: Denel Aeronautics | C52: =IFERROR(VLOOKUP($B52,Company_Cat!$B$2:$H$623,6,FALSE),"") | F52: Product & Service Enquiries | H52: marketing@denelaviation.co.za | I52: 27137413654
A53: =IFERROR(VLOOKUP($B53,Company_Cat!$B$2:$E$623,2,FALSE),"") | B53: Henley Air Technical | C53: =IFERROR(VLOOKUP($B53,Company_Cat!$B$2:$H$623,6,FALSE),"") | H53: info@henleyair.co.za | I53: 27118275503
A54: =IFERROR(VLOOKUP($B54,Company_Cat!$B$2:$E$623,2,FALSE),"") | B54: NRG EXPLORATION CC | C54: =IFERROR(VLOOKUP($B54,Company_Cat!$B$2:$H$623,6,FALSE),"") | D54: Catherine | E54: Kruse | F54: Sales & Marketing Manager | G54: 27745109916 | H54: catherine.kruse@nrgex.co.za
A55: =IFERROR(VLOOKUP($B55,Company_Cat!$B$2:$E$623,2,FALSE),"") | B55: Starlite Maintenance Durban (Pty) Ltd | C55: =IFERROR(VLOOKUP($B55,Company_Cat!$B$2:$H$623,6,FALSE),"") | D55: Ockert | E55: Smit | F55: Regional Head of Maintenance | H55: ockerts@starliteaviation.com | I55: 27315716600
A56: =IFERROR(VLOOKUP($B56,Company_Cat!$B$2:$E$623,2,FALSE),"") | B56: Trio Helicopters & Aviation | C56: =IFERROR(VLOOKUP($B56,Company_Cat!$B$2:$H$623,6,FALSE),"") | D56: Frans | E56: Grobbelaar | F56: Manager | G56: 27825608808 | H56: trioavi@netactive.co.za | I56: 27116591022
A57: =IFERROR(VLOOKUP($B57,Company_Cat!$B$2:$E$623,2,FALSE),"") | B57: Acher Aviation | C57: =IFERROR(VLOOKUP($B57,Company_Cat!$B$2:$H$623,6,FALSE),"") | H57: admin@acheraviation.com | I57: 27315632650
A58: =IFERROR(VLOOKUP($B58,Company_Cat!$B$2:$E$623,2,FALSE),"") | B58: Airwork Aviation Maintenance Division (Pty) Ltd | C58: =IFERROR(VLOOKUP($B58,Company_Cat!$B$2:$H$623,6,FALSE),"") | D58: Mike | E58: Hall | F58: General Manager | G58: 27824440855
A59: =IFERROR(VLOOKUP($B59,Company_Cat!$B$2:$E$623,2,FALSE),"") | B59: Breytech Aviation cc | C59: =IFERROR(VLOOKUP($B59,Company_Cat!$B$2:$H$623,6,FALSE),"") | D59: Willie | E59: Breytenbach | H59: info@breytech.co.za | I59: 27125673139
A60: =IFERROR(VLOOKUP($B60,Company_Cat!$B$2:$E$623,2,FALSE),"") | B60: Paramount Aerospace Systems | C60: =IFERROR(VLOOKUP($B60,Company_Cat!$B$2:$H$623,6,FALSE),"") | H60: info@paramountgroup.biz | I60: 27108229200
A61: =IFERROR(VLOOKUP($B61,Company_Cat!$B$2:$E$623,2,FALSE),"") | B61: Starlite Maintenance | C61: =IFERROR(VLOOKUP($B61,Company_Cat!$B$2:$H$623,6,FALSE),"") | H61: enquiries@starliteaviation.com | I61: 27105937772
A62: =IFERROR(VLOOKUP($B62,Company_Cat!$B$2:$E$623,2,FALSE),"") | B62: Hover Dynamics Maintenance CC | C62: =IFERROR(VLOOKUP($B62,Company_Cat!$B$2:$H$623,6,FALSE),"") | D62: Yolande | E62: van der Merwe | F62: Emergency Contact | H62: reception@hoverdynamics.co.za | I62: 27135900550
A63: =IFERROR(VLOOKUP($B63,Company_Cat!$B$2:$E$623,2,FALSE),"") | B63: SAPS AIRWING | C63: =IFERROR(VLOOKUP($B63,Company_Cat!$B$2:$H$623,6,FALSE),"") | D63: Lt Col TP | E63: Mathopa | F63: Support Head | H63: mathopaT@saps.gov.za | I63: 27124327536
A64: =IFERROR(VLOOKUP($B64,Company_Cat!$B$2:$E$623,2,FALSE),"") | B64: Aeronautic Solutions (Pty) Ltd | C64: =IFERROR(VLOOKUP($B64,Company_Cat!$B$2:$H$623,6,FALSE),"") | D64: Renier | E64: Pieterse | F64: Accountable Manager | I64: 27113121443
A65: =IFERROR(VLOOKUP($B65,Company_Cat!$B$2:$E$623,2,FALSE),"") | B65: Warbird Aircraft Services CC | C65: =IFERROR(VLOOKUP($B65,Company_Cat!$B$2:$H$623,6,FALSE),"") | D65: Johannes Hendrik | E65: Lock | F65: Member | I65: 27125430544
A66: =IFERROR(VLOOKUP($B66,Company_Cat!$B$2:$E$623,2,FALSE),"") | B66: FFA Aviation | C66: =IFERROR(VLOOKUP($B66,Company_Cat!$B$2:$H$623,6,FALSE),"") | H66: amo@kishugu.com | I66: 27137418222
A67: =IFERROR(VLOOKUP($B67,Company_Cat!$B$2:$E$623,2,FALSE),"") | B67: Leading Edge Helicopters cc | C67: =IFERROR(VLOOKUP($B67,Company_Cat!$B$2:$H$623,6,FALSE),"") | F67: Accountable Manager | I67: 27137415582
A68: =IFERROR(VLOOKUP($B68,Company_Cat!$B$2:$E$623,2,FALSE),"") | B68: Savannah Helicopter Maintenance | C68: =IFERROR(VLOOKUP($B68,Company_Cat!$B$2:$H$623,6,FALSE),"") | D68: Petrus | E68: La Grange | F68: Chief Engineer / Accountable Manager | G68: 27824660204
A69: =IFERROR(VLOOKUP($B69,Company_Cat!$B$2:$E$623,2,FALSE),"") | B69: Superior Aeroworx | C69: =IFERROR(VLOOKUP($B69,Company_Cat!$B$2:$H$623,6,FALSE),"") | D69: Eddie | E69: Pienaar | F69: Director / Chief Engineer | G69: 27765952120 | H69: eddiep@superiorair.co.za | I69: 27110365921
A70: =IFERROR(VLOOKUP($B70,Company_Cat!$B$2:$E$623,2,FALSE),"") | B70: Orsmond Aviation | C70: =IFERROR(VLOOKUP($B70,Company_Cat!$B$2:$H$623,6,FALSE),"")
A71: =IFERROR(VLOOKUP($B71,Company_Cat!$B$2:$E$623,2,FALSE),"") | C71: =IFERROR(VLOOKUP($B71,Company_Cat!$B$2:$H$623,6,FALSE),"")
A72: =IFERROR(VLOOKUP($B72,Company_Cat!$B$2:$E$623,2,FALSE),"") | C72: =IFERROR(VLOOKUP($B72,Company_Cat!$B$2:$H$623,6,FALSE),"")
A73: =IFERROR(VLOOKUP($B73,Company_Cat!$B$2:$E$623,2,FALSE),"") | C73: =IFERROR(VLOOKUP($B73,Company_Cat!$B$2:$H$623,6,FALSE),"")
A74: =IFERROR(VLOOKUP($B74,Company_Cat!$B$2:$E$623,2,FALSE),"") | C74: =IFERROR(VLOOKUP($B74,Company_Cat!$B$2:$H$623,6,FALSE),"")
A75: =IFERROR(VLOOKUP($B75,Company_Cat!$B$2:$E$623,2,FALSE),"") | C75: =IFERROR(VLOOKUP($B75,Company_Cat!$B$2:$H$623,6,FALSE),"")
A76: =IFERROR(VLOOKUP($B76,Company_Cat!$B$2:$E$623,2,FALSE),"") | C76: =IFERROR(VLOOKUP($B76,Company_Cat!$B$2:$H$623,6,FALSE),"")
A77: =IFERROR(VLOOKUP($B77,Company_Cat!$B$2:$E$623,2,FALSE),"") | C77: =IFERROR(VLOOKUP($B77,Company_Cat!$B$2:$H$623,6,FALSE),"")
A78: =IFERROR(VLOOKUP($B78,Company_Cat!$B$2:$E$623,2,FALSE),"") | C78: =IFERROR(VLOOKUP($B78,Company_Cat!$B$2:$H$623,6,FALSE),"")
A79: =IFERROR(VLOOKUP($B79,Company_Cat!$B$2:$E$623,2,FALSE),"") | C79: =IFERROR(VLOOKUP($B79,Company_Cat!$B$2:$H$623,6,FALSE),"")
A80: =IFERROR(VLOOKUP($B80,Company_Cat!$B$2:$E$623,2,FALSE),"") | C80: =IFERROR(VLOOKUP($B80,Company_Cat!$B$2:$H$623,6,FALSE),"")
A81: =IFERROR(VLOOKUP($B81,Company_Cat!$B$2:$E$623,2,FALSE),"") | C81: =IFERROR(VLOOKUP($B81,Company_Cat!$B$2:$H$623,6,FALSE),"")
A82: =IFERROR(VLOOKUP($B82,Company_Cat!$B$2:$E$623,2,FALSE),"") | C82: =IFERROR(VLOOKUP($B82,Company_Cat!$B$2:$H$623,6,FALSE),"")
... A1000: =IFERROR(VLOOKUP($B1000,Company_Cat!$B$2:$E$623,2,FALSE),"") | C1000: =IFERROR(VLOOKUP($B1000,Company_Cat!$B$2:$H$623,6,FALSE),"")

Sheet Company_Notes
A1: C_ID | B1: Company | C1: Order | D1: Notes
A2: =IFERROR(VLOOKUP($B2,Company_Cat!$B$2:$E$623,2,FALSE),"") | B2: Santam Aviation | D2: Santam Aviation (a dedicated division) is widely regarded as South Africa’s leading aviation insurer, covering a wide range of private and corporate aircraft. They are known for financial stability and a strong track record, making them a reliable partner for aircraft coverage.
A3: =IFERROR(VLOOKUP($B3,Company_Cat!$B$2:$E$623,2,FALSE),"") | B3: iTOO Special Risks (Hollard) | D3: heir policies (for hull, third-party liability, etc.) are comprehensive yet simplified, and backed by Hollard’s financial strength.
A4: =IFERROR(VLOOKUP($B4,Company_Cat!$B$2:$E$623,2,FALSE),"") | B4: Old Mutual Insure | D4: Old Mutual’s Specialty Insurance division handles large and niche risks (e.g. engineering, marine) and can insure general aviation as part of bespoke solutions.
A5: =IFERROR(VLOOKUP($B5,Company_Cat!$B$2:$E$623,2,FALSE),"") | B5: Infiniti Insurance | D5: Infiniti’s collaborative approach and growing presence in aviation insurance can be an opportunity – they are open to innovative solutions and have a flexible partnership philosophy
A6: =IFERROR(VLOOKUP($B6,Company_Cat!$B$2:$E$623,2,FALSE),"") | B6: Natsure (Guardrisk) | D6: their aviation insurance solutions (including aircraft hull and liability, drone cover, etc.) are underwritten by Guardrisk Insurance, a leading cell-captive insurer
A7: =IFERROR(VLOOKUP($B7,Company_Cat!$B$2:$E$623,2,FALSE),"") | B7: Natsure (Guardrisk) | D7: Natsure’s broad broker network across Southern Africa means they insure many private and commercial aircraft via various brokers, making them a noteworthy player in GA insurance.
A8: =IFERROR(VLOOKUP($B8,Company_Cat!$B$2:$E$623,2,FALSE),"") | B8: AIG South Africa | D8: AIG’s aerospace division, for instance, offers policies for everything from “small aircraft operators to major airline manufacturers,” with dedicated aviation claims teams worldwide
A9: =IFERROR(VLOOKUP($B9,Company_Cat!$B$2:$E$623,2,FALSE),"") | B9: Lloyd’s of London | D9: active via local brokers
A10: =IFERROR(VLOOKUP($B10,Company_Cat!$B$2:$E$623,2,FALSE),"") | B10: DJA Aviation (Dennis Jankelow & Associates) | D10: DJA is South Africa’s largest dedicated aviation insurance broker, with a team that represents the greatest concentration of aviation insurance expertise on the continent
A11: =IFERROR(VLOOKUP($B11,Company_Cat!$B$2:$E$623,2,FALSE),"") | B11: DJA Aviation (Dennis Jankelow & Associates) | D11: DJA arranges cover for a huge number of private and commercial aircraft owners. They balance cost, coverage, and service for clients, working with various underwriters (Santam, Lloyd’s, etc.)
A12: =IFERROR(VLOOKUP($B12,Company_Cat!$B$2:$E$623,2,FALSE),"") | B12: Airborne Insurance Consultants (PSG Insure) | D12: PSG Insure became one of the biggest aviation brokers after acquiring Airborne Insurance Consultants, which was Africa’s fastest-growing independent aviation specialist
A13: =IFERROR(VLOOKUP($B13,Company_Cat!$B$2:$E$623,2,FALSE),"") | B13: Airborne Insurance Consultants (PSG Insure) | D13: The merged PSG aviation division has a substantial client footprint across South Africa and insures over 1,000 aircraft owners (post-acquisition)
... A32: =IFERROR(VLOOKUP($B32,Company_Cat!$B$2:$E$623,2,FALSE),"") | B32: AIG South Africa | D32: Cost-efficient, flexible protection, and superior hull and liability coverage for owners, operators, and aircraft management companies
A33: =IFERROR(VLOOKUP($B33,Company_Cat!$B$2:$E$623,2,FALSE),"") | B33: AIG South Africa | C33: 1 | D33: Supplier Registration Done - Check AIG Supplier One Dashboard for Appearances etc.
A34: =IFERROR(VLOOKUP($B34,Company_Cat!$B$2:$E$623,2,FALSE),"") | B34: MCC Aviation(PTY) Ltd | D34: Helicopter AMO - Lanseria
A35: =IFERROR(VLOOKUP($B35,Company_Cat!$B$2:$E$623,2,FALSE),"") | B35: Lady Lori Kenya Limited | D35: Luxury helicopter charter and aero‑medical services in East Africa.
A36: =IFERROR(VLOOKUP($B36,Company_Cat!$B$2:$E$623,2,FALSE),"") | B36: Lady Lori Kenya Limited | D36: AMO Services
A37: =IFERROR(VLOOKUP($B37,Company_Cat!$B$2:$E$623,2,FALSE),"") | B37: Ferreira Aviation CC | C37: 1 | D37: Clear indication that they need to be able to order by Serial number - need to convert from Acryl Form
A38: =IFERROR(VLOOKUP($B38,Company_Cat!$B$2:$E$623,2,FALSE),"") | B38: Lowveld Aircraft Services CC | D38: Everyone might be dead or business sold
A39: =IFERROR(VLOOKUP($B39,Company_Cat!$B$2:$E$623,2,FALSE),"")
A40: =IFERROR(VLOOKUP($B40,Company_Cat!$B$2:$E$623,2,FALSE),"")
A41: =IFERROR(VLOOKUP($B41,Company_Cat!$B$2:$E$623,2,FALSE),"")
A42: =IFERROR(VLOOKUP($B42,Company_Cat!$B$2:$E$623,2,FALSE),"")
A43: =IFERROR(VLOOKUP($B43,Company_Cat!$B$2:$E$623,2,FALSE),"")
A44: =IFERROR(VLOOKUP($B44,Company_Cat!$B$2:$E$623,2,FALSE),"")
A45: =IFERROR(VLOOKUP($B45,Company_Cat!$B$2:$E$623,2,FALSE),"")
A46: =IFERROR(VLOOKUP($B46,Company_Cat!$B$2:$E$623,2,FALSE),"")
A47: =IFERROR(VLOOKUP($B47,Company_Cat!$B$2:$E$623,2,FALSE),"")
A48: =IFERROR(VLOOKUP($B48,Company_Cat!$B$2:$E$623,2,FALSE),"")
A49: =IFERROR(VLOOKUP($B49,Company_Cat!$B$2:$E$623,2,FALSE),"")
A50: =IFERROR(VLOOKUP($B50,Company_Cat!$B$2:$E$623,2,FALSE),"")
... A623: =IFERROR(VLOOKUP($B623,Company_Cat!$B$2:$E$623,2,FALSE),"")

Sheet Company_Addresses
A1: C_ID | B1: Company | C1: Type | D1: Airport
A2: =IFERROR(VLOOKUP($B2,Company_Cat!$B$2:$E$623,2,FALSE),"") | B2: Flightsure | C2: Postal | D2: N/A | E2: PO.Box 5072, Halfway House, 1685
A3: =IFERROR(VLOOKUP($B3,Company_Cat!$B$2:$E$623,2,FALSE),"") | B3: Flightsure | C3: Head | E3: Block 2, First Floor South, Waterfall Terraces, Waterfall Park, Bekker Road, Midrand
A4: =IFERROR(VLOOKUP($B4,Company_Cat!$B$2:$E$623,2,FALSE),"") | B4: Arc Aviation (Aircraft Risk Company) | C4: Head | E4: Level 1, Block C, Cedar Tree Office Park, Cnr Cedar Road and Stinkwood Close, Broadacres
A5: =IFERROR(VLOOKUP($B5,Company_Cat!$B$2:$E$623,2,FALSE),"") | B5: AIG South Africa | C5: Joburg | E5: 1st Floor, Sandown Mews West, 88 Stella Street, Sandown 2196 PO Box 31983, Braamfontein 2017, South Africa
A6: =IFERROR(VLOOKUP($B6,Company_Cat!$B$2:$E$623,2,FALSE),"") | B6: Orsmond Aviation | C6: Head | E6: Bethlehem
A7: =IFERROR(VLOOKUP($B7,Company_Cat!$B$2:$E$623,2,FALSE),"") | B7: Capital Air (Pty) Ltd | C7: Head | D7: Rand | E7: Hanger 3H-Rand Airport, Germiston 1401
A8: =IFERROR(VLOOKUP($B8,Company_Cat!$B$2:$E$623,2,FALSE),"") | B8: NAC Helicopter Division | C8: Head | E8: Rand Airport, Lanseria International Airport, Lanseria, 1748
A9: =IFERROR(VLOOKUP($B9,Company_Cat!$B$2:$E$623,2,FALSE),"") | B9: MCC Aviation(PTY) Ltd | C9: Head | E9: Hangar 43, Gate 5, Lanseria International Airport
A10: =IFERROR(VLOOKUP($B10,Company_Cat!$B$2:$E$623,2,FALSE),"") | B10: Transvaal Aircraft Maintenance (Pty) Ltd | C10: Head | E10: 3 Hanger, Wonderboom Airport, Pretoria, 0182
A11: =IFERROR(VLOOKUP($B11,Company_Cat!$B$2:$E$623,2,FALSE),"") | B11: PRECISION AVIATION SERVICES (PTY) Ltd | C11: Head | E11: Hangar 109, Lintvelt Avenue, Wonderboom Airport, Pretoria, 0182P.O. Box 81958, Doornpoort, Pretoria, 0017
A12: =IFERROR(VLOOKUP($B12,Company_Cat!$B$2:$E$623,2,FALSE),"") | B12: BAC Aviation (Pty) Ltd | C12: Head | E12: Imbonini Helistop, 4 Barbet Road, Shakas Head, KZN 4399
A13: =IFERROR(VLOOKUP($B13,Company_Cat!$B$2:$E$623,2,FALSE),"") | B13: Ferreira Aviation CC | C13: Head | E13: Hangar B4, New Tempe Airport, Kenilworth Road, Bainsvlei, Bloemfontein
A14: =IFERROR(VLOOKUP($B14,Company_Cat!$B$2:$E$623,2,FALSE),"") | B14: Ferreira Aviation CC | C14: Satelite | E14: Ferreira Aviation, George Airport, General area, George
A15: =IFERROR(VLOOKUP($B15,Company_Cat!$B$2:$E$623,2,FALSE),"") | B15: Vektor Aviation | C15: Head | E15: 296 Glenwood Road, Lynnwood Park, Pretoria, 0081
A16: =IFERROR(VLOOKUP($B16,Company_Cat!$B$2:$E$623,2,FALSE),"") | B16: Vektor Aviation | C16: Satelite | E16: Block A, Nicol on Main Office Park 2, Bruton Road, Bryanston, Johannesburg
A17: =IFERROR(VLOOKUP($B17,Company_Cat!$B$2:$E$623,2,FALSE),"") | B17: Greystones Aviaton Components (Pty) Ltd | C17: Head | E17: 1146 Chris Hani Road, Durban, 4000
A18: =IFERROR(VLOOKUP($B18,Company_Cat!$B$2:$E$623,2,FALSE),"") | B18: Hover Dynamics Maintenance CC | C18: Head | E18: Hanger M, Grand Central Airport, Midrand
A19: =IFERROR(VLOOKUP($B19,Company_Cat!$B$2:$E$623,2,FALSE),"") | B19: Heli-Fix cc | C19: Head | E19: Hangar 37, Wonderboom Airport, Pretoria 0182PO Box 80602, Doornpoort, Pretoria 0017
... A37: =IFERROR(VLOOKUP($B37,Company_Cat!$B$2:$E$623,2,FALSE),"") | B37: Superior Aeroworx | C37: Head | E37: No 3 New Road, Main Terminal Building, Grand Central Airport, Midrand, Gauteng, 1685, South Africa
A38: =IFERROR(VLOOKUP($B38,Company_Cat!$B$2:$E$623,2,FALSE),"")
A39: =IFERROR(VLOOKUP($B39,Company_Cat!$B$2:$E$623,2,FALSE),"")
A40: =IFERROR(VLOOKUP($B40,Company_Cat!$B$2:$E$623,2,FALSE),"")
A41: =IFERROR(VLOOKUP($B41,Company_Cat!$B$2:$E$623,2,FALSE),"")
A42: =IFERROR(VLOOKUP($B42,Company_Cat!$B$2:$E$623,2,FALSE),"")
A43: =IFERROR(VLOOKUP($B43,Company_Cat!$B$2:$E$623,2,FALSE),"")
A44: =IFERROR(VLOOKUP($B44,Company_Cat!$B$2:$E$623,2,FALSE),"")
A45: =IFERROR(VLOOKUP($B45,Company_Cat!$B$2:$E$623,2,FALSE),"")
A46: =IFERROR(VLOOKUP($B46,Company_Cat!$B$2:$E$623,2,FALSE),"")
A47: =IFERROR(VLOOKUP($B47,Company_Cat!$B$2:$E$623,2,FALSE),"")
A48: =IFERROR(VLOOKUP($B48,Company_Cat!$B$2:$E$623,2,FALSE),"")
A49: =IFERROR(VLOOKUP($B49,Company_Cat!$B$2:$E$623,2,FALSE),"")
... A1000: =IFERROR(VLOOKUP($B1000,Company_Cat!$B$2:$E$623,2,FALSE),"")

Sheet CAA
A1: Midrand Office AMOs (Head Office)
A2: # | B2: AMO Number | C2: NAME | D2: CATEGORIES | E2: MAIN/ SATELLITE | F2: LOCATION | H2: Category | I2: Scope of Work
A3: 1 | B3: 1 | C3: South African Airways Technical SOC | D3: A, B, C, D, W, X, NDT & Special Processes | E3: Main Base | F3: O.R. Tambo - SAAT Area | H3: A | I3: Line maintenance on aircraft airframes (release to service, minor assembly, certifying install and test/ferry flights)
A4: 2 | B4: 2 | C4: Capital Air (Pty) Ltd | D4: B, D, E & W | E4: Main Base | F4: Rand Airport | H4: B | I4: Component-level maintenance for airframes and accessories (rotorcraft excluded from engine)
A5: 3 | B5: 3 | C5: Century Avionics CC | D5: X & W | E5: Main Base | F5: Lanseria | H5: C | I5: On‑wing maintenance for engines (non‑rotorcraft), including test flight release
A6: 4 | B6: 4 | C6: NAC Lanseria | D6: A,B ,C, W & X | E6: Main Base | F6: Lanseria | H6: D | I6: Rack-level engine work (overhaul, repair, modifications), plus manufacture of parts under CAR 21
A7: 5 | B7: 8 | C7: Roesch Aviation | D7: B | E7: Main Base | F7: Lanseria | H7: E | I7: Rotorcraft and rotorcraft‑engine maintenance (airframe/engine installs, overhaul, rotors, test‑flight release)
A8: 6 | B8: 12 | C8: Aircraft Powerplant Company (Pty) Ltd | D8: C, D, X & SPECIAL PROCESSES | E8: Main Base | F8: Wonderboom | H8: W | I8: Installation and maintenance of aircraft electrical, instrument, and radio systems across all aircraft classes
A9: 7 | B9: 22 | C9: Aero Natal (Pty) Ltd | D9: A, B, C, D, | E9: Main Base | F9: Durban-Virginia Airport | H9: X | I9: Overhaul, repair, testing, modification, and limited manufacture of equipment, instruments, components, accessories, auxiliaries, parts (e.g. propellers class X4, welding class X5)
A10: 8 | B10: 27 | C10: NAC Helicopter Division | D10: B, D, E, W , X WELDING & NDT | E10: Main Base | F10: Rand Airport
A11: 9 | B11: 28 | C11: Vector Aerospace Africa (Pty) Ltd | D11: C, D & SPECIAL PROCESSES NDT | E11: Main Base | F11: Lanseria
A12: 10 | B12: 33 | C12: North East Avionics CC | D12: X & W | E12: Main Base | F12: Nelspruit
A13: 11 | B13: 40 | C13: Nicholson Helicopters CC | D13: B & E | E13: Main Base | F13: Rand Airport
A14: 12 | B14: 43 | C14: South African Air Force - 21Squadron | D14: A, C & W | E14: Main Base | F14: Waterkloof AFB
A15: 13 | B15: 48 | C15: Skycare Maintenance | D15: A, B & C | E15: Main Base | F15: Lanseria
A16: 14 | B16: 51 | C16: Dart Aeronautical (Pty) Ltd | D16: X & W | E16: Main Base | F16: Rand Airport
A17: 15 | B17: 52 | C17: SA Airlink | D17: A, B, C, X & W | E17: Main Base | F17: O.R. Tambo
A18: 16 | B18: 53 | C18: Turbine Versions (Pty) Ltd | D18: A, B, C & W | E18: Main Base | F18: Wonderboom
A19: 17 | B19: 54 | C19: Aztec Electronics (Pty) Ltd | D19: X | E19: Main Base | F19: Elandsfontein
A20: 18 | B20: 56 | C20: Lowveld Aircraft Services CC | D20: A, B, C & W | E20: Main Base | F20: Nelspruit
A21: 19 | B21: 57 | C21: Dentec Avionics ( Amended from Complete Avionics Systems (PTY) LTD) | D21: W & X | E21: Main Base | F21: Wonderboom
... A84: 82 | B84: 803 | C84: Lufthanza Technik AG | D84: A, C, D, W, X, NDT & SPECIAL PROCESSES | E84: Main Base | F84: Germany, Hamburg
D85: D, X, NDT & SPECIAL PROCESSES | E85: Satellite-Stations | F85: Germany - Munich
D86: A, B, C, D, W, X, NDT & SPECIAL PROCESSES | F86: Germany - Frankfurt
D87: A, C & W | F87: Malta
D88: A, C & W | F88: Hungary
D89: A, B, C, W & NDT | F89: Bulgaria
D90: B & NDT | F90: UK
D91: A, C & W | F91: Germany-Alzey
A92: 83 | B92: 810 | C92: Blue Bird Aviation | D92: A,C & W | E92: Main Base | F92: Khartoum, Sudan
A93: 84 | B93: 813 | C93: Academy Air | D93: A & C | E93: Main Base | F93: Rand Airport
A94: 85 | B94: 816 | C94: Executive Air Zimbabwe | D94: A, C, W & X | E94: Main Base | F94: Zimbabwe- Prince Charles
A95: 86 | B95: 824 | C95: Starlite Maintenance Durban (Pty) Ltd | D95: B ,E & W | E95: Main Base | F95: Durban-Virginia Airport
A96: 87 | B96: 829 | C96: Turbo Prop Service Centre Uganda Ltd | D96: A, C & W | E96: Main Base | F96: Uganda
A97: 88 | B97: 830 | C97: Heli-Afrique | D97: B & E | E97: Main Base | F97: Rand Airport
A98: 89 | B98: 844 | C98: Superior Millenium Aircraft Engines CC | D98: A, B, C, D & NTCA | E98: Main Base | F98: Springs Airfield
A99: 90 | B99: 846 | C99: Trio Helicopters & Aviation | D99: B & E | E99: Main Base | F99: Lanseria
A100: 91 | B100: 849 | C100: Vector Aerospace Engine Services Atlantic | D100: D & SPECIAL PROCESSES | E100: Main Base | F100: Canada
A101: 92 | B101: 852 | C101: Acher Aviation | D101: B & E | E101: Main Base | F101: Durban-Virginia Airport
A102: 93 | B102: 854 | C102: Ethiopian Airlines | D102: A, B, C, D, W, X & NDT | E102: Main Base | F102: Ethiopian
A103: 94 | B103: 874 | C103: Solenta Aviation (Pty) Ltd | D103: A, B, C, W & X | E103: Main Base | F103: Fourways (Office) & O.R. Tambo (Hangar)
... A257: 3 | B257: 1045 | C257: SA Red Cross Air Mercy Service | D257: A, C, E & W | E257: Main Base | F257: Cape Town
D258: A, C, E & W | E258: Satellite-Station | F258: Durban
D259: E | E259: Satellite-Station | F259: Oudtshoorn
A260: 4 | B260: 1236 | C260: FliteTech (Pty) Ltd | D260: E & W | E260: Main Base | F260: Cape Town
A261: 5 | B261: 1386 | C261: Whip-Air Aviation | D261: A, B, C & W | E261: Main Base | F261: Cape Town, Wellington
A262: 6 | B262: 619 | C262: Cape Aircraft Interiors | D262: B & E | E262: Main Base | F262: Cape Town
A263: 7 | B263: 1326 | C263: Mac Air NDT Solutions | D263: NDT | E263: Main Base | F263: Cape Town
D264: A,C & E | E264: Main Base | F264: Cape Town
D265: A,C & E | E265: Satellite-Station | F265: Mozambique -Benguerra Island
A266: 8 | B266: 1388 | C266: East Coast Aviation (Pty) LTD | D266: A,C & E | E266: Satellite-Station | F266: Mozambique- Quilaea Islands
D267: A,C & E | E267: Satellite-Station | F267: Namibia - Luderitz
D268: A,C & E | E268: Satellite-Station | F268: Durban - Virginia
D269: A,C & E | E269: Satellite-Station | F269: Springbok Airfield
A270: 9 | B270: 1425 | C270: Normair | D270: B | E270: Main Base | F270: Cape Town
A271: 10 | B271: 1426 | C271: Ultimax Aviation (Pty) Ltd | D271: E | E271: Main Base | F271: Cape Town
A272: 11 | B272: 46 | C272: 43 Air School | D272: A, B, C , D, E, W & X | E272: Main Base | F272: Port Alfred
A273: 12 | B273: 1029 | C273: Master Tech Aircraft Maintenance | D273: A, B, C and Specialized Processes | E273: Main Base | F273: Cape Town, Robertson Airfield
A274: 13 | B274: 1398 | C274: Diepkloof Aircraft Maintenance (Highveld Aircraft Maintenance t/a) | D274: A, B and C | E274: Main Base | F274: Cape Town, Malmesbury
A275: 14 | B275: 195 | C275: Falconair (Pty) Ltd | D275: A, B, C, W & X | E275: Main Base | F275: Cape Town
A276: 15 | B276: 1209 | C276: TFASA Engineering (Pearl Coral 1173 CC t/a) | D276: A, C & E | E276: Main Base | F276: Oudtshoorn
D277: A, C & E | E277: Satellite-Station | F277: Cape Town, George
D278: A, C, and E | E278: Satellite-Station | F278: Beaufort West
A279: 16 | B279: 1439 | C279: Intergrated Avionic Solutions George | D279: W & X | E279: Main Base | F279: George
A280: 17 | B280: 1263 | C280: Heli-Air Aviation (Pty) Ltd | D280: B & E | E280: Main Base | F280: Cape Town - Mossel Bay
D281: E | E281: Satellite-Station | F281: Kimberley
A282: 18 | B282: 1097 | C282: AREF Avionics | D282: W & X | E282: Main Base | F282: Port Alfred
A283: 19 | B283: 196 | C283: SA Mooney Sales and Services CC | D283: A, B, C & W | E283: Main Base | F283: Port Alfred
A284: 20 | B284: 1216 | C284: MOBBS PROPERTIES CC T/A Aircraft Assembly & Upholstery Centre | D284: A; B; C & W | E284: Main Base | F284: Port Elizabeth
A285: 21 | B285: 1267 | C285: Sideslip Aviation Worx t/a Slideslip (Pty) ltd | D285: A, B, C, E & W | E285: Main Base | F285: Cape Town - Morningstar Airfield
A286: 22 | B286: 49 | C286: Titanoffshore (Pty) Ltd | D286: A, B, C, E, W & X | E286: Main Base | F286: George, Industrial Area
D287: E & W | E287: Satellite-Station | F287: George Airport
D288: A, B, C, E, W & X | E288: Satellite-Station | F288: Namibia - Oranjemund
A289: 23 | B289: 224 | C289: Flicape (Pty) Ltd | D289: A, C & W | E289: Main Base | F289: Cape Town
A290: 24 | B290: 1244 | C290: Douglas Aviation (Pty) LTD | D290: A, B, C & D | E290: Main Base | F290: Port Elizabeth
D291: A & C | E291: Satellite-Station | F291: Plattenberg Bay
A292: 25 | B292: 909 | C292: Shadow Lite CC | D292: A, B, C & Ds | E292: Main Base | F292: George
A293: 26 | B293: 1422 | C293: RAW Maintenance | D293: A, B,C, E & W | E293: Main Base | F293: Cape Town
A294: 27 | B294: 918 | C294: Aircraft Instruments CC | D294: W & X | E294: Main Base | F294: Cape Town
A295: 28 | B295: 1424 | C295: North Cape Aviation | D295: E | E295: Main Base | F295: Kimberley
A296: 29 | B296: 89 | C296: Progress Aviation (Pty) Ltd | D296: A, B & C | E296: Main Base | F296: Port Elizabeth, Green Bushes
A297: 30 | B297: 23 | C297: Wineland Ballooning CC t/a Wineland Balloon Workshop | D297: A & B | E297: Main Base | F297: Cape Town, Paarl
A298: 31 | B298: 222 | C298: Air Hart Aircraft CC. | D298: A, B, C, D, E, W & X | E298: Main Base | F298: East London
A299: 32 | B299: 1605 | C299: Bay Aircraft Services | D299: A,B,C & W | E299: Main Base | F299: Port Elizabeth
A300: 33 | B300: 172 | C300: Aquila Air Services | D300: A, B, C & W | E300: Main Base | F300: George
A301: 34 | B301: 182 | C301: Stellair CC | D301: A, B, C, W & X | E301: Main Base | F301: Stellenbosch
A302: 35 | B302: 1020 | C302: Sport Aviation | D302: E | E302: Main Base | F302: Cape Town
A303: 36 | B303: 1309 | C303: Rotary Air Force SA Pty Ltd | D303: A, C, D, E, W & X | E303: Main Base | F303: Upington
... A306: 41 | B306: 1522 | C306: British Airways Engineering | D306: A,C & W | E306: Main Base | F306: UK
A307: 42 | D307: A,C & W | E307: Satellite-Station | F307: Nigeria - Lagos
A308: 43 | D308: A,C & W | E308: Satellite-Station | F308: USA- Washington
A309: 44 | B309: 1399 | C309: GE Aircraft Engine Services | D309: C,D & Special processes | E309: Main Base | F309: UK
A310: 45 | B310: 1340 | C310: Dassault Falcon Service | D310: A,B, C, D, W, X, NDT & Special Processes | E310: Main Base | F310: France
A311: 46 | B311: 1529 | C311: Cathay Pacific | D311: A,C & W | E311: Main Base | F311: China, Hong Kong

Sheet Aviation Codes
A1: C_ID | B1: Company | C1: Code
A2: =IFERROR(VLOOKUP($B2,Company_Cat!$B$2:$E$623,2,FALSE),"")
A3: =IFERROR(VLOOKUP($B3,Company_Cat!$B$2:$E$623,2,FALSE),"")
A4: =IFERROR(VLOOKUP($B4,Company_Cat!$B$2:$E$623,2,FALSE),"")
A5: =IFERROR(VLOOKUP($B5,Company_Cat!$B$2:$E$623,2,FALSE),"")
A6: =IFERROR(VLOOKUP($B6,Company_Cat!$B$2:$E$623,2,FALSE),"")
A7: =IFERROR(VLOOKUP($B7,Company_Cat!$B$2:$E$623,2,FALSE),"")
A8: =IFERROR(VLOOKUP($B8,Company_Cat!$B$2:$E$623,2,FALSE),"")
A9: =IFERROR(VLOOKUP($B9,Company_Cat!$B$2:$E$623,2,FALSE),"")
A10: =IFERROR(VLOOKUP($B10,Company_Cat!$B$2:$E$623,2,FALSE),"")
A11: =IFERROR(VLOOKUP($B11,Company_Cat!$B$2:$E$623,2,FALSE),"")
A12: =IFERROR(VLOOKUP($B12,Company_Cat!$B$2:$E$623,2,FALSE),"")
A13: =IFERROR(VLOOKUP($B13,Company_Cat!$B$2:$E$623,2,FALSE),"")
... A1000: =IFERROR(VLOOKUP($B1000,Company_Cat!$B$2:$E$623,2,FALSE),"")

Sheet Sheet

Sheet Sheet 1
A1: Insurance | B1: Broker
A2: Santam Aviation, | B2: Aerospace Underwriting Managers
A3: Hollard/iTOO Special Risks,
A4: Bryte Insurance, and
A5: AIG South Africa
A6: Azriel Aviation and
A7: Osprey,
A8: international carriers Global Aerospace and
A9: Allianz Commercial that operate through Johannesburg brokers | B9: Compass Ins.
A10: Global Aerospace
A11: Chubb & WTW

Sheet Flight schools
A1: School | B1: Contact person (role) | C1: Phone | D1: Email | E1: Addresses | F1: Planes | G1: Website | H1: Description type
A2: Lanseria Flight Centre (TBD) | B2: Ian Dyson (Director); Mark Hardcastle (Chief Flight Instructor) | C2: +27 11 312 5166 | D2: info@flylfc.com | H2: HELICOPTER OR LIGHT AIRCRAFT
A3: Aeronav Academy (Lanseria) | B3: Donald O’Connor (Managing Director) | C3: +27 11 701 3862 | D3: info@aeronav.co.za | E3: Friday 03/10/2025 Reach Out
A4: Skyhawk Aviation (Lanseria) | B4: Mohamed Lashin (Chief Flight Instructor) | C4: +27 11 701 2622 | D4: info@skyhawk.co.za
A5: Blue Chip Flight School (Wonderboom, PTA) | B5: Brendon Lubbe (Chief Flight Instructor) | C5: +27 12 543 3050 | D5: marketing@bluechip-avia.co.za
A6: Eagle Air (Wonderboom, PTA) | B6: General contact | C6: Web form | D6: info@eagleair.co.za
A7: Superior Pilot Services (SPS, Grand Central) | B7: General contact | C7: +27 11 805 0605 | D7: info@superiorair.co.za
A8: Flight Training Services – FTS (Grand Central) | B8: General contact | C8: +27 11 805 9015 / 9016 | D8: fly@fts.co.za
A9: Central Flying Academy (Rand, Germiston) | B9: Erna Krebs (Chief Flight Instructor / Director) | C9: +27 11 824 4421 | D9: info@cfasa.co.za
A10: Johannesburg School of Flying (Rand, Germiston) | B10: Siphiwe Richard Khoza (Chief Flight Instructor) | C10: +27 11 827 9827 / 824 3990 | D10: info@jsf.co.za
A11: U-Fly Training Academy (Rand, Germiston) | B11: Dr Robert Gobac (Chief Flying Instructor) | C11: +27 11 824 0680 | D11: info@uflyacademy.co.za
A12: Eagle1 Flight Academy (Rand, Germiston) | B12: DJ Lubbe (Chief Flight Instructor) | C12: +27 11 824 1396; +27 79 448 8289 | D12: info@eagle1.co.za
A13: Airborne Aviation (Brakpan/Benoni) | B13: Seymour “Sluggy” Lugg (Chief Flying Instructor) | C13: +27 74 113 2911 | D13: info@airborneaviation.co.za
A14: Johannesburg Flying Academy (Panorama, Alberton) | B14: Russell Best (Chief Flight Instructor) | C14: +27 64 756 6356 (office); +27 65 969 8873 (Shamir Orrie) | D14: info@jhbflying.co.za
A15: Sun Quest Aviation (Rand, Germiston) | B15: General contact | C15: +27 81 309 3113 | D15: info@sqasa.co.za
... A19: Middelburg Aero Club – Flight School (i-Flight Aviation) Middelburg Airfield (FAMB) | B19: Francois Barnard | C19: +27 63 104 6163 | D19: info@i-flight.co.za
A20: AFOS Flight Training School | B20: Training Office | C20: +27 11 827 4125; +27 83 327 6333 | D20: fly@afos.co.za; mark@afos.co.za | E20: Hangar 40, Lancaster Ave, Rand Airport 1419 | F20: — | G20: http://www.afos.co.za | H20: Fixed-wing training at Rand Airport | I20: Fixed-wing
A21: Aeronav Academy | B21: Admissions Office | C21: +27 11 701 3862 | D21: info@aeronav.co.za | E21: Gate 9A, Lanseria International Airport | F21: Diamond DA20; Cessna 172; Diamond DA42 | G21: https://www.aeronav.co.za | H21: Lanseria ATO; single & multi-engine training; FNPT II | I21: Fixed-wing
A22: Bluebird Aerospace Flight School | B22: Training Office | C22: +27 71 480 4513 | D22: info@bluebirdaerospace.com | E22: Vereeniging Airport (FAVV), 121 Citation Rd, Aeroval | F22: Cessna 150; Cessna 172; Piper Cherokee | G22: https://bluebirdaerospace.com/ | H22: Fixed-wing flight school at Vereeniging | I22: Fixed-wing
A23: Central Flying Academy (CFA) | B23: Erna Krebs (Chief Flight Instructor) | C23: +27 11 824 4421 | D23: info@cfasa.co.za | E23: Hangar 28, Hurricane Rd, Rand Airport, Germiston 1401 | F23: Cessna 172; Cessna 172RG; Piper PA-30 Twin Comanche | G23: https://www.cfasa.co.za | H23: Fixed-wing ATO at Rand Airport; PPL→CPL/IF; FNPT II available | I23: Fixed-wing
A24: Eagle1 Flight Academy | B24: Training Office | C24: +27 11 824 1396; +27 79 448 8289 | D24: info@eagle1.co.za | E24: Hangar 20, Rand Airport, Germiston 1401 | F24: — | G24: https://www.eagle1.co.za | H24: Fixed-wing flight school at Rand Airport | I24: Fixed-wing
A25: Helivate Helicopter Services | B25: Training Team | C25: +27 60 969 3317; +27 72 219 3264; +27 84 583 1569 | D25: info@helivate.com | E25: Jack Taylor Airport, Barta Street, Krugersdorp | F25: Robinson R44; Robinson R66; Alouette III | G25: https://www.helivate.com/ | H25: Helicopter pilot training; Gauteng base at Krugersdorp | I25: Helicopter | K25: paul@helivate.com | L25: paul@statusmark.co.za | M25: Paul Cumming
A26: Henley Air Flight Training | B26: Flight School Office | C26: +27 11 827 5503 | D26: flightschool@henleyair.co.za | E26: Hangar 6, Rand Airport, Germiston 1419 | F26: Robinson R44; Bell 206 JetRanger; Bell 407 | G26: https://www.henleyairflighttraining.co.za/ | H26: Helicopter pilot training (PPL→ATPL) at Rand | I26: Helicopter
A27: Hover Dynamics | B27: Andre Snyman (Head of Training) | C27: +27 11 315 1834 | D27: reception@hoverdynamics.co.za | E27: Grand Central Airport Terminal Building, New Road, Midrand | F27: Robinson R22; Robinson R44; Robinson R66 | G27: https://hoverdynamics.co.za/ | H27: Helicopter pilot training at Grand Central | I27: Helicopter | K27: hdm@hoverdynamics.co.za | L27: ame@hoverdynamics.co.za | M27: DEAN | N27: FELDMAN | O27: dean@hoverdynamics.co.za
A28: Johannesburg School of Flying (JSF) | B28: Training Office | C28: +27 11 827 9827; +27 11 824 3990 | D28: info@jsf.co.za | E28: Hangars 30–33, Rand Airport, Germiston 1401 | F28: Cessna 152; Cessna 172; Piper PA-34 Seneca II | G28: https://jsf.co.za | H28: Fixed-wing training at Rand Airport; multi-engine available | I28: Fixed-wing
A29: Lanseria Flight Centre (LFC) | B29: Ian Dyson (Director) | C29: +27 11 312 5166; +27 60 829 0953 | D29: info@flylfc.com | E29: Terminal Building, Office Suite 25B, Grand Central Airport, Midrand | F29: Cessna 172; Diamond DA42; Piper PA-34 Seneca | G29: https://www.flylfc.com | H29: Fixed-wing training at Grand Central; integrated & modular | I29: Fixed-wing
A30: NAC Helicopter Flight Training (National Airways Corporation) | B30: Vicky Sankey (Training/Exams) | C30: +27 11 345 2500 | D30: flightschool@nac.co.za; info@nac.co.za | E30: Rand Airport, Germiston (Training) & Ultimate Heliport, Midrand | F30: Robinson R22; Robinson R44; Bell 206/407 | G30: https://www.nac.co.za/helicopter-pilot-training | H30: Helicopter flight training (NAC) | I30: Helicopter
A31: Phoebus Apollo Aviation (Flight School) | B31: Flight School Office | C31: +27 11 824 3814 | D31: flightschool@phoebusapollo.co.za | E31: Hangars 17 & 21, Rand Airport, Germiston 1401 | F31: Cessna 152; Cessna 172/172RG; Piper PA-34 Seneca I | G31: https://www.phoebusapollo.co.za | H31: Fixed-wing training and charter | I31: Fixed-wing
A32: Skyhawk Aviation | B32: Training Office | C32: +27 11 701 2622 | D32: info@skyhawk.co.za | E32: Hangar 30, Gate 5, Lanseria International Airport | F32: Cessna 172; Piper PA-28; Piper PA-34 Seneca | G32: https://skyhawk.co.za | H32: Fixed-wing training; career pilot programmes | I32: Fixed-wing
A33: Sun Quest Aviation (SQA) | B33: Ops/Enquiries | C33: +27 81 309 3113; +27 11 827 9308 | D33: info@sqasa.co.za | E33: Hangar 4, Rand Airport, Germiston 1401 | F33: — | G33: https://sqasa.co.za/ | H33: Fixed-wing ATO at Rand Airport | I33: Fixed-wing
A34: U-Fly Training Academy | B34: Training Office | C34: +27 11 824 0680; +27 11 027 7655 | D34: info@uflyacademy.co.za | E34: 1 Spitfire Crescent, Rand Airport, Germiston | F34: Piper PA-28 Warrior; Piper PA-28R Arrow; Piper PA-34 Seneca | G34: https://www.uflyacademy.co.za | H34: Fixed-wing training and hire-&-fly; PPL→ATPL pathway | I34: Fixed-wing
A35: Superior Pilot Services (SPS) | B35: Training Office | C35: +27 11 805 0605 | D35: info@superiorair.co.za | E35: Grand Central Airport (FAGC), Midrand, Gauteng | F35: Cessna 172 | G35: https://www.superiorpilotservices.com | H35: Fixed-wing ATO at Grand Central; PPL, Night, CPL etc. | I35: Fixed-wing
A36: Flight Training Services (FTS) | B36: Training Office | C36: +27 11 805 9015 | D36: fly@fts.co.za | E36: Grand Central Airport (FAGC), Midrand, Gauteng | F36: Cessna 172 | G36: https://www.fts.co.za | H36: Fixed-wing ATO; PPL through CPL/IR; based at Grand Central. | I36: Fixed-wing
A37: Blue Chip Flight School | B37: Training Office | C37: +27 12 543 3050 | D37: marketing@bluechip-avia.co.za | E37: Main Terminal Building, Wonderboom National Airport (FAWB), Pretoria | F37: Cessna 172 | G37: https://bluechipflightschool.co.za | H37: Large Wonderboom-based ATO offering PPL → CPL/IR. | I37: Fixed-wing
A38: Eagle Air Flight School | B38: Training Office | C38: +27 12 543 1929 | D38: info@eagleair.co.za | E38: Wonderboom National Airport (FAWB), Pretoria | F38: Cessna 172; Piper PA-28; Beechcraft Baron | G38: https://eagleair.co.za | H38: Comprehensive fixed-wing training at Wonderboom. | I38: Fixed-wing
A39: Loutzavia Flight Training Academy | B39: Training Office | C39: +27 12 543 1620 | D39: info@loutzavia.co.za | E39: Wonderboom National Airport (FAWB), Pretoria | F39: (not publicly listed on site) | G39: https://loutzavia.com | H39: Fixed-wing ATO; PPL → advanced ratings at Wonderboom. | I39: Fixed-wing
... A41: Professional Flight Centre (PFC) | B41: Training Office | C41: +27 12 567 0575 | D41: pfc1161@gmail.com | E41: Wonderboom National Airport (FAWB), Pretoria | F41: Cessna 172 | G41: https://www.professionalflightcentre.co.za | H41: Fixed-wing ATO at Wonderboom; PPL, Night, CPL. | I41: Fixed-wing
A42: Flyfofa Aviation & Training | B42: Training Office | C42: +27 12 543 5798 | D42: info@flyfofa.co.za | E42: Wonderboom National Airport (FAWB), Pretoria | F42: (not publicly listed on site) | G42: https://flyfofa.co.za | H42: Fixed-wing ATO at Wonderboom; ab-initio and advanced. | I42: Fixed-wing | K42: BRUCE | L42: FISHA | M42: fisha@flyfofa.co.za | N42: bfisha@flyfofa.co.za | O42: reception@flyfofa.co.za | R42: Website: https://www.flyfofa.co.za
A43: Airborne Aviation (Brakpan) | B43: Training Office | C43: +27 76 564 2722 | D43: info@airborne-aviation.co.za | E43: Brakpan/Benoni Airfield (FABB), Gauteng | F43: Cessna 172; Cessna 182; Piper Seneca | G43: https://airborne-aviation.co.za | H43: Fixed-wing ATO at Brakpan/Benoni; PPL → CPL/ME. | I43: Fixed-wing
A44: Mach1 Aviation Flight Academy | B44: Training Office | C44: +27 11 743 3305 | D44: info@mach1aviation.co.za | E44: Springs Airfield (FASI), Springs, Gauteng | F44: (not publicly listed on site) | G44: https://www.mach1aviation.co.za | H44: Fixed-wing ATO at Springs; PPL → CPL with on-site lodging. | I44: Fixed-wing
A45: Aviatech FAPS Flight Academy | B45: Training Office | C45: +27 83 235 8043 | D45: info@fapsflightacademy.co.za | E45: Potchefstroom Airfield (FAPS), North West | F45: (not publicly listed on site) | G45: https://fapsflightacademy.co.za | H45: Fixed-wing ATO at Potchefstroom; PPL and advanced. | I45: Fixed-wing
A46: Apex Flight Academy (Bucephalus Air) | B46: Training Office | C46: +27 76 692 7352 | D46: info@bucephalusair.co.za | E46: Klerksdorp Airfield (FAKD), North West | F46: (not publicly listed on site) | G46: https://bucephalusair.co.za | H46: Fixed-wing ATO at Klerksdorp; ab-initio to advanced. | I46: Fixed-wing
A47: Witbank Aeronautical Association Flight School | B47: Erik Maasdorp | C47: +27 82 897 4817 | D47: ppl@flywaa.co.za | E47: Witbank Airport (FAWI), Emalahleni, Mpumalanga | F47: (not publicly listed on site) | G47: https://www.facebook.com/groups/WitbankAero | H47: Club-based flight training at Witbank (fixed-wing). | I47: Fixed-wing
A48: Johannesburg Flying Academy | B48: Training Office | C48: +27 82 201 6230 | D48: info@jhbflying.co.za | E48: Panorama Airfield, Johannesburg South (Eikenhof), Gauteng | F48: (not publicly listed on site) | G48: https://www.jhbflying.co.za | H48: Fixed-wing ATO at Panorama; PPL, Night, hour-building. | I48: Fixed-wing
A49: Accolade Flying Wings (Rand) | B49: Training Office | C49: +27 60 985 6622 | D49: info@accoladeflyingwings.co.za | E49: Hangar 54, Rand Airport, 4 Viking Way, Germiston, Gauteng | F49: Tecnam P92; Cessna 172 (Jet-A1); Diamond DA42 | G49: https://accoladeflyingwings.co.za | H49: Fixed-wing ATO at Rand; PPL → CPL/ME; diversified training fleet. | I49: Fixed-wing

Sheet FL extended
A1: Aeronav Academy (Lanseria) | C1: Sent
A2: Donald O'Connor | B2: donald@aeronav.co.za | C2: x
A3: Donald O' Connor | B3: donald.oconnor@aeronav.co.za | C3: x | E3: Friday 03/10/2025 Reach Out
B4: info@aeronav.co.za
A5: Central Flying Academy (Rand, Germiston)
A6: BARTER PAUL RONALD | B6: paul@cfa.co.za | C6: x
A7: MARAIS WILLEM KAREL NICOLAAS | B7: willie@cfa.co.za | C7: x
B8: info@cfasa.co.za
A10: Airborne Aviation (Brakpan/Benoni) | B10: sam@airborneaviation.co.za | C10: x
D16: info@mach1aviation.co.za
A20: AFOS Flight Training School | B20: Training Office | C20: +27 11 827 4125; +27 83 327 6333 | D20: fly@afos.co.za; mark@afos.co.za | E20: Hangar 40, Lancaster Ave, Rand Airport 1419 | F20: — | G20: http://www.afos.co.za | H20: Fixed-wing training at Rand Airport | I20: Fixed-wing
A21: Aeronav Academy | B21: Admissions Office | C21: +27 11 701 3862 | D21: info@aeronav.co.za | E21: Gate 9A, Lanseria International Airport | F21: Diamond DA20; Cessna 172; Diamond DA42 | G21: https://www.aeronav.co.za | H21: Lanseria ATO; single & multi-engine training; FNPT II | I21: Fixed-wing
A22: Bluebird Aerospace Flight School | B22: Training Office | C22: +27 71 480 4513 | D22: info@bluebirdaerospace.com | E22: Vereeniging Airport (FAVV), 121 Citation Rd, Aeroval | F22: Cessna 150; Cessna 172; Piper Cherokee | G22: https://bluebirdaerospace.com/ | H22: Fixed-wing flight school at Vereeniging | I22: Fixed-wing
A23: Central Flying Academy (CFA) | B23: Erna Krebs (Chief Flight Instructor) | C23: +27 11 824 4421 | D23: info@cfasa.co.za | E23: Hangar 28, Hurricane Rd, Rand Airport, Germiston 1401 | F23: Cessna 172; Cessna 172RG; Piper PA-30 Twin Comanche | G23: https://www.cfasa.co.za | H23: Fixed-wing ATO at Rand Airport; PPL→CPL/IF; FNPT II available | I23: Fixed-wing
A24: Eagle1 Flight Academy | B24: Training Office | C24: +27 11 824 1396; +27 79 448 8289 | D24: info@eagle1.co.za | E24: Hangar 20, Rand Airport, Germiston 1401 | F24: — | G24: https://www.eagle1.co.za | H24: Fixed-wing flight school at Rand Airport | I24: Fixed-wing
A25: Helivate Helicopter Services | B25: Training Team | C25: +27 60 969 3317; +27 72 219 3264; +27 84 583 1569 | D25: info@helivate.com | E25: Jack Taylor Airport, Barta Street, Krugersdorp | F25: Robinson R44; Robinson R66; Alouette III | G25: https://www.helivate.com/ | H25: Helicopter pilot training; Gauteng base at Krugersdorp | I25: Helicopter | K25: paul@helivate.com | L25: paul@statusmark.co.za | M25: Paul Cumming
A26: Henley Air Flight Training | B26: Flight School Office | C26: +27 11 827 5503 | D26: flightschool@henleyair.co.za | E26: Hangar 6, Rand Airport, Germiston 1419 | F26: Robinson R44; Bell 206 JetRanger; Bell 407 | G26: https://www.henleyairflighttraining.co.za/ | H26: Helicopter pilot training (PPL→ATPL) at Rand | I26: Helicopter
A27: Hover Dynamics | B27: Andre Snyman (Head of Training) | C27: +27 11 315 1834 | D27: cfi@hoverdynamics.co.za; reception@hoverdynamics.co.za | E27: Grand Central Airport Terminal Building, New Road, Midrand | F27: Robinson R22; Robinson R44; Robinson R66 | G27: https://hoverdynamics.co.za/ | H27: Helicopter pilot training at Grand Central | I27: Helicopter | K27: hdm@hoverdynamics.co.za | L27: ame@hoverdynamics.co.za | M27: DEAN | N27: FELDMAN | O27: dean@hoverdynamics.co.za
A28: Johannesburg School of Flying (JSF) | B28: Training Office | C28: +27 11 827 9827; +27 11 824 3990 | D28: info@jsf.co.za | E28: Hangars 30–33, Rand Airport, Germiston 1401 | F28: Cessna 152; Cessna 172; Piper PA-34 Seneca II | G28: https://jsf.co.za | H28: Fixed-wing training at Rand Airport; multi-engine available | I28: Fixed-wing
A29: Lanseria Flight Centre (LFC) | B29: Ian Dyson (Director) | C29: +27 11 312 5166; +27 60 829 0953 | D29: info@flylfc.com | E29: Terminal Building, Office Suite 25B, Grand Central Airport, Midrand | F29: Cessna 172; Diamond DA42; Piper PA-34 Seneca | G29: https://www.flylfc.com | H29: Fixed-wing training at Grand Central; integrated & modular | I29: Fixed-wing
A30: NAC Helicopter Flight Training (National Airways Corporation) | B30: Vicky Sankey (Training/Exams) | C30: +27 11 345 2500 | D30: flightschool@nac.co.za; info@nac.co.za | E30: Rand Airport, Germiston (Training) & Ultimate Heliport, Midrand | F30: Robinson R22; Robinson R44; Bell 206/407 | G30: https://www.nac.co.za/helicopter-pilot-training | H30: Helicopter flight training (NAC) | I30: Helicopter
A31: Phoebus Apollo Aviation (Flight School) | B31: Flight School Office | C31: +27 11 824 3814 | D31: flightschool@phoebusapollo.co.za | E31: Hangars 17 & 21, Rand Airport, Germiston 1401 | F31: Cessna 152; Cessna 172/172RG; Piper PA-34 Seneca I | G31: https://www.phoebusapollo.co.za | H31: Fixed-wing training and charter | I31: Fixed-wing
A32: Skyhawk Aviation | B32: Training Office | C32: +27 11 701 2622 | D32: info@skyhawk.co.za | E32: Hangar 30, Gate 5, Lanseria International Airport | F32: Cessna 172; Piper PA-28; Piper PA-34 Seneca | G32: https://skyhawk.co.za | H32: Fixed-wing training; career pilot programmes | I32: Fixed-wing
A33: Sun Quest Aviation (SQA) | B33: Ops/Enquiries | C33: +27 81 309 3113; +27 11 827 9308 | D33: info@sqasa.co.za | E33: Hangar 4, Rand Airport, Germiston 1401 | F33: — | G33: https://sqasa.co.za/ | H33: Fixed-wing ATO at Rand Airport | I33: Fixed-wing
A34: U-Fly Training Academy | B34: Training Office | C34: +27 11 824 0680; +27 11 027 7655 | D34: info@uflyacademy.co.za | E34: 1 Spitfire Crescent, Rand Airport, Germiston | F34: Piper PA-28 Warrior; Piper PA-28R Arrow; Piper PA-34 Seneca | G34: https://www.uflyacademy.co.za | H34: Fixed-wing training and hire-&-fly; PPL→ATPL pathway | I34: Fixed-wing
A35: Superior Pilot Services (SPS) | B35: Training Office | C35: +27 11 805 0605 | D35: info@superiorair.co.za | E35: Grand Central Airport (FAGC), Midrand, Gauteng | F35: Cessna 172 | G35: https://www.superiorpilotservices.com | H35: Fixed-wing ATO at Grand Central; PPL, Night, CPL etc. | I35: Fixed-wing
A36: Flight Training Services (FTS) | B36: Training Office | C36: +27 11 805 9015 | D36: fly@fts.co.za | E36: Grand Central Airport (FAGC), Midrand, Gauteng | F36: Cessna 172 | G36: https://www.fts.co.za | H36: Fixed-wing ATO; PPL through CPL/IR; based at Grand Central. | I36: Fixed-wing
A37: Blue Chip Flight School | B37: Training Office | C37: +27 12 543 3050 | D37: marketing@bluechip-avia.co.za | E37: Main Terminal Building, Wonderboom National Airport (FAWB), Pretoria | F37: Cessna 172 | G37: https://bluechipflightschool.co.za | H37: Large Wonderboom-based ATO offering PPL → CPL/IR. | I37: Fixed-wing
A38: Eagle Air Flight School | B38: Training Office | C38: +27 12 543 1929 | D38: info@eagleair.co.za | E38: Wonderboom National Airport (FAWB), Pretoria | F38: Cessna 172; Piper PA-28; Beechcraft Baron | G38: https://eagleair.co.za | H38: Comprehensive fixed-wing training at Wonderboom. | I38: Fixed-wing
A39: Loutzavia Flight Training Academy | B39: Training Office | C39: +27 12 543 1620 | D39: info@loutzavia.co.za | E39: Wonderboom National Airport (FAWB), Pretoria | F39: (not publicly listed on site) | G39: https://loutzavia.com | H39: Fixed-wing ATO; PPL → advanced ratings at Wonderboom. | I39: Fixed-wing
... A41: Professional Flight Centre (PFC) | B41: Training Office | C41: +27 12 567 0575 | D41: pfc1161@gmail.com | E41: Wonderboom National Airport (FAWB), Pretoria | F41: Cessna 172 | G41: https://www.professionalflightcentre.co.za | H41: Fixed-wing ATO at Wonderboom; PPL, Night, CPL. | I41: Fixed-wing
A42: Flyfofa Aviation & Training | B42: Training Office | C42: +27 12 543 5798 | D42: info@flyfofa.co.za | E42: Wonderboom National Airport (FAWB), Pretoria | F42: (not publicly listed on site) | G42: https://flyfofa.co.za | H42: Fixed-wing ATO at Wonderboom; ab-initio and advanced. | I42: Fixed-wing | K42: BRUCE | L42: FISHA | M42: fisha@flyfofa.co.za | N42: bfisha@flyfofa.co.za | O42: reception@flyfofa.co.za
A43: Airborne Aviation (Brakpan) | B43: Training Office | C43: +27 76 564 2722 | D43: info@airborne-aviation.co.za | E43: Brakpan/Benoni Airfield (FABB), Gauteng | F43: Cessna 172; Cessna 182; Piper Seneca | G43: https://airborne-aviation.co.za | H43: Fixed-wing ATO at Brakpan/Benoni; PPL → CPL/ME. | I43: Fixed-wing
A44: Mach1 Aviation Flight Academy | B44: Training Office | C44: +27 11 743 3305 | D44: info@mach1aviation.co.za | E44: Springs Airfield (FASI), Springs, Gauteng | F44: (not publicly listed on site) | G44: https://www.mach1aviation.co.za | H44: Fixed-wing ATO at Springs; PPL → CPL with on-site lodging. | I44: Fixed-wing
A45: Aviatech FAPS Flight Academy | B45: Training Office | C45: +27 83 235 8043 | D45: info@fapsflightacademy.co.za | E45: Potchefstroom Airfield (FAPS), North West | F45: (not publicly listed on site) | G45: https://fapsflightacademy.co.za | H45: Fixed-wing ATO at Potchefstroom; PPL and advanced. | I45: Fixed-wing
A46: Apex Flight Academy (Bucephalus Air) | B46: Training Office | C46: +27 76 692 7352 | D46: info@bucephalusair.co.za | E46: Klerksdorp Airfield (FAKD), North West | F46: (not publicly listed on site) | G46: https://bucephalusair.co.za | H46: Fixed-wing ATO at Klerksdorp; ab-initio to advanced. | I46: Fixed-wing
A47: Witbank Aeronautical Association Flight School | B47: Training Office | C47: +27 82 976 4103 | D47: info@witbankaeroclub.co.za | E47: Witbank Airport (FAWI), Emalahleni, Mpumalanga | F47: (not publicly listed on site) | G47: https://www.facebook.com/groups/WitbankAero | H47: Club-based flight training at Witbank (fixed-wing). | I47: Fixed-wing
A48: Johannesburg Flying Academy | B48: Training Office | C48: +27 82 201 6230 | D48: info@jhbflying.co.za | E48: Panorama Airfield, Johannesburg South (Eikenhof), Gauteng | F48: (not publicly listed on site) | G48: https://www.jhbflying.co.za | H48: Fixed-wing ATO at Panorama; PPL, Night, hour-building. | I48: Fixed-wing
A49: Accolade Flying Wings (Rand) | B49: Training Office | C49: +27 60 985 6622 | D49: info@accoladeflyingwings.co.za | E49: Hangar 54, Rand Airport, 4 Viking Way, Germiston, Gauteng | F49: Tecnam P92; Cessna 172 (Jet-A1); Diamond DA42 | G49: https://accoladeflyingwings.co.za | H49: Fixed-wing ATO at Rand; PPL → CPL/ME; diversified training fleet. | I49: Fixed-wing

Sheet 10-10-25 Capture
B1: School | C1: Contact person (role) | D1: Phone | E1: Email | F1: Addresses | G1: Planes | H1: Website | I1: Description | J1: Type
B2: 43 Air School | C2: Attie Niemann — Chief Executive Officer | D2: +27 46 604 3600 | E2: fly@43airschool.com | F2: Port Alfred Campus, Private Bag X43, Port Alfred 6170 | G2: Cessna 172; Piper PA-28; Beechcraft Baron (multi) | H2: https://www.43airschool.com/ | I2: Large integrated ATO with multi-base operations and Boeing-approved ATPL programs. | J2: Fixed-wing
B3: Progress Flight Academy | C3: John English — CEO Owner | D3: +27 41 451 1196 | E3: info@flightacademy.co.za | F3: Port Elizabeth International Airport, Walmer, Gqeberha | G3: Piper Warrior III (PA-28-161); Cessna 172; Piper Seneca | H3: https://www.flightacademy.co.za/ | I3: Professional pilot training at Gqeberha (Port Elizabeth) with proven fleet for airline pathways. | J3: Fixed-wing
B4: Algoa Flying Club (Flight School) | C4: Michael Thompson — Chief Flying Instructor | D4: +27 41 581 3274 | E4: info@algoafc.co.za | F4: Port Elizabeth International Airport, 10 Forest Hill Dr, Walmer, Gqeberha | G4: Cessna 172; Sling 2; Piper Arrow (PA-28R) | H4: https://algoafc.co.za/flight-school/ | I4: Not‑for‑profit flying club with SACAA ATO; long-standing ab‑initio to advanced training. | J4: Fixed-wing
B5: Madiba Bay School of Flight | C5: Gerhard van Eeden — Owner Accountable Manager | D5: +27 41 581 2040 | E5: info@madibabayschoolofflight.co.za | F5: Port Elizabeth International Airport, Gqeberha | G5: Sling 2; Cessna 172; Piper Twin Comanche (PA-30) | H5: https://www.madibabayschoolofflight.co.za/ | I5: Ab‑initio to advanced training with Sling and legacy Piper types. | J5: Fixed-wing
B6: Aptrac Aviation | C6: Ian Judd — Chief Flight Instructor | D6: +27 41 581 0300 | E6: info@aptrac.co.za | F6: Port Elizabeth, Eastern Cape | G6: Cessna 172; Piper PA-28; Robinson R22 | H6: https://www.bestaviation.net/school/aptrac_aviation/ | I6: Fixed‑wing and helicopter training (per directory listing). | J6: Fixed-wing and Helicopter
B7: PTC Aviation | C7: Wayne Westoby — Director | D7: +27 87 943 7100 | E7: info@ptcaviation.co.za | F7: 30 Edward Street, Richmond Hill, Gqeberha (Port Elizabeth), 6001 | G7: N/A (Airline training, APS MCC/A320/B737) | H7: https://www.ptcaviation.co.za/ | I7: Advanced airline-readiness training (APS MCC, A320/B737) rather than ab‑initio. | J7: Ground/Sim
B8: Border Aviation Club and Flight School | C8: Russell Best — Chief Flying Instructor | D8: +27 43 736 6181 | E8: info@borderaviation.co.za | F8: East London Airport and Wings Park (EL); Queenstown Airfield | G8: Piper Archer (PA-28-181); Cessna 172; Sling 2 | H8: https://borderaviation.co.za/ | I8: Club and ATO with three bases offering specialised training environments. | J8: Fixed-wing
B9: Flight Training College (FTC) | C9: Walter Waldeck — Chief Executive Officer | D9: +27 44 876 9055 | E9: ftc@flighttraining.co.za | F9: Hangar 27, George Airport, George, Western Cape | G9: Cessna 152; Cessna 172; Beechcraft Duchess 76 | H9: https://flighttraining.co.za/ | I9: Garden Route-based ATO with single and multi-engine fleet and FNPT II simulator. | J9: Fixed-wing
B10: Starlite Aviation Training Academy | C10: Gustav Grunewald — Head of Training Academy Accountable Manager | D10: +27 31 571 6600 | E10: train@starliteaviation.com | F10: Durban (Virginia Airport) and Mossel Bay, Western Cape | G10: Robinson R22; Robinson R44; Guimbal Cabri G2 | H10: https://www.starliteaviation.com/training/ | I10: Large helicopter (and some fixed‑wing) training academy with Durban and Mossel Bay bases. | J10: Helicopter (+FW)
B11: Virginia Flight School | C11: Douglas Fraser — Chief Executive Officer | D11: +27 31 563 2080 | E11: info@vfs.co.za | F11: 220 Fairway, Virginia Airport, Durban North, 4051 | G11: Piper PA-28-140/160; Cessna 172; Piper Seneca II | H11: https://vfs.co.za/ | I11: Fixed‑wing ATO at Virginia Airport with single and multi‑engine training. | J11: Fixed-wing
B12: Pietermaritzburg Aero Club and Flight School | C12: Telani Lithgow — Chief Flying Instructor | D12: +27 33 386 1256 | E12: info@pmbac.co.za | F12: Oribi Airport, Pietermaritzburg | G12: Sling 2; Cessna 150; Cessna 172 | H12: https://pmbac.co.za/flight-training/ | I12: Historic aero club with active ATO and modernised training fleet. | J12: Fixed-wing
... B18: Westline Aviation | C18: Charlie Marais — Chief Executive Officer | D18: +27 51 451 1717 | E18: info@westline.co.za | F18: 2B New Tempe Airport, Kenilworth Rd, Bloemfontein | G18: Robinson R22; Robinson R44; Cessna 172 | H18: https://www.facebook.com/westlineaviation/ | I18: Offers both helicopter and fixed‑wing training at Tempe, Bloemfontein. | J18: Fixed-wing and Helicopter
A19: Duplicate | B19: Eagle Flight Academy (Bloemfontein/Hartswater) | C19: D. J. Lubbe — Chief Flying Instructor (also referenced as owner/senior instructor) | D19: +27 51 007 0007 | E19: training@eagleflight.co.za | F19: Stand B5, New Tempe Airport, Kenilworth Rd, Bloemfontein 9300 | G19: Cessna 172; Piper Aztec/Seneca; Mooney M20C (complex) | H19: https://eagleflight.co.za/ | I19: Fixed‑wing ATO with single, complex and multi‑engine training and FNPT II. | J19: Fixed-wing
B20: Bloem Flying School | C20: Not publicly listed | D20: +27 82 458 4141 | E20: info@bloemflyingschool.co.za | F20: New Tempe Airport, Bloemfontein | G20: Cessna 150; Cessna 172; Light Sport (LSA) | H20: https://m.facebook.com/bloemflyingschool/about/ | I20: Microlight/LSA and PPL training at Tempe. | J20: Fixed-wing
B21: Mid Air Charter and Training | C21: Not publicly listed | D21: +27 51 451 1225 | E21: — | F21: Tempe Airport, 2312 Kenilworth Rd, Bloemfontein | G21: Cessna 172; Piper PA-28; Cessna 150 | H21: https://www.thinklocal.co.za/biz/mid-air-charter-and-training-bloemfontein | I21: Charter and ATO providing ab‑initio training at Tempe. | J21: Fixed-wing
B22: Fantini Air Flight Academy | C22: Not publicly listed | D22: +27 56 212 8474 | E22: info@fantiniair.co.za | F22: Kroonstad Airport, Free State | G22: Cessna 172; Piper PA-28; Sling 2 | H22: https://fantiniair.co.za/ | I22: Kroonstad-based flight academy and AMO (SACAA/1094). | J22: Fixed-wing
B23: Grace Air | C23: Not publicly listed | D23: — | E23: — | F23: Kroonstad Airport, Free State | I23: Unable to verify active flight school operations from current public sources. | J23: —
B24: Paramount Aviation Academy | C24: Not publicly listed | D24: +27 58 303 1439 | E24: admin@flyparamount.co.za | F24: Bethlehem Airport, Free State | G24: Cessna 172; Piper PA-28; Beechcraft Baron/BE76 | H24: https://flyparamount.co.za/ | I24: Bethlehem-based ATO with controlled airfield and on‑field ATC/VOR. | J24: Fixed-wing
B25: Lowveld Aero Club (Flight School) | C25: Not publicly listed | D25: +27 13 741 2146 | E25: admin@lac.co.za | F25: Nelspruit Airfield (FANS), Mbombela | G25: Cessna 172; Sling 2; Piper PA-28 | H25: https://lac.co.za/ | I25: Aero club offering flight training and hangarage at Nelspruit. | J25: Fixed-wing
B26: Saphire Blue Flight Training | C26: Not publicly listed | D26: — | E26: — | F26: Mbombela (Nelspruit) | G26: Sling 2; Cessna 172; Robinson R44 (affiliate) | H26: https://klcbt.co.za/saphire-blue/ | I26: Aviation company with fixed‑wing and helicopter services; limited public ATO details. | J26: Fixed-wing and Helicopter
B27: Kishugu Flight Academy | C27: Not publicly listed | D27: +27 13 753 7500 | E27: info@kishugu.com | F27: Kishugu Aviation, 6 Copper Crescent, Nelspruit 1200 | G27: Robinson R44; Cessna 172; Bell 206 | H27: https://kishugu.com/contact/ | I27: Part of Kishugu Aviation (firefighting); provides pilot training and operations. | J27: Fixed-wing and Helicopter
B28: OFA Ermelo Flight School (MyWings) | C28: Not publicly listed | D28: +27 71 837 7363 | E28: info@mywings.co.za | F28: Office 1, Ermelo Airport, Ermelo, Mpumalanga | G28: Sling 2; Cessna 172; Piper PA-28 | H28: https://mywings.co.za/flight-school/ | I28: Outeniqua Flight Academy/‘MyWings’ branding; fixed‑wing PPL/CPL and charter. | J28: Fixed-wing
B29: Leading Edge Flight School | C29: Not publicly listed | D29: +27 15 793 2585 | E29: training@lefsa.co.za | F29: Hoedspruit Civil Airfield, Hoedspruit | G29: Cessna 172; Piper PA-28; Sling 2 | H29: https://www.leadingedgeflight.co.za/ | I29: Lowveld-based ATO at Hoedspruit offering PPL to CPL. | J29: Fixed-wing
B30: Limpopo Flight School | C30: Not publicly listed | D30: +27 15 288 0069 | E30: info@limpopoflightschool.co.za | F30: Polokwane Airport, Limpopo | G30: Cessna 172; Piper PA-28; Sling 2 | H30: https://limpopoflightschool.co.za/ | I30: Polokwane-based ATO providing fixed‑wing training. | J30: Fixed-wing
B31: Heritage Aviation | C31: Not publicly listed | D31: +27 79 867 2244 | E31: fly@heritageaviation.co.za | F31: Swellendam Airport, Western Cape | G31: Sling 2; Cessna 172; Piper PA-28 | H31: https://www.heritageaviation.co.za/ | I31: ATO at Swellendam offering scenic area training and hire and fly. | J31: Fixed-wing
